{
  "strategy": "Alpha Relaxation (Percentile-based PBR/ROE)",
  "total_return": 21.892699,
  "annual_return": 0.199362,
  "final_equity": 228926993.0,
  "sharpe_ratio": 0.9424,
  "sortino_ratio": 1.1674,
  "max_drawdown": 0.32599,
  "calmar_ratio": 0.6116,
  "volatility": 0.210496,
  "total_trades": 243,
  "win_rate": 0.6255,
  "profit_factor": 2.9983,
  "avg_holding_days": 308.5,
  "avg_impact_bps": 22.8,
  "max_aum_supported_b": 30.0,
  "walk_forward": {
    "training": {
      "phase": "training",
      "start_date": "2007-01-01",
      "end_date": "2015-12-31",
      "total_return": 3.389834,
      "annual_return": 0.178719,
      "sharpe_ratio": 0.7705,
      "sortino_ratio": 0.9819,
      "max_drawdown": 0.066918,
      "total_trades": 100,
      "win_rate": 0.61,
      "profit_factor": 3.4608,
      "trades": [
        {
          "code": "30920",
          "entry_date": "2008-08-05",
          "exit_date": "2008-11-06",
          "entry_price": 42.6,
          "exit_price": 26.7,
          "shares": 23474,
          "pnl": -373236.60000000003,
          "pnl_pct": -0.37323943661971837,
          "impact_bps": 9.2663,
          "phase": "training",
          "composite_score": 0.9741379310344827
        },
        {
          "code": "24130",
          "entry_date": "2008-08-05",
          "exit_date": "2008-11-06",
          "entry_price": 166.3,
          "exit_price": 129.2,
          "shares": 6013,
          "pnl": -223082.30000000013,
          "pnl_pct": -0.223090799759471,
          "impact_bps": 7.8381,
          "phase": "training",
          "composite_score": 0.9568965517241379
        },
        {
          "code": "90220",
          "entry_date": "2008-08-05",
          "exit_date": "2008-11-06",
          "entry_price": 2322.0,
          "exit_price": 1676.0,
          "shares": 430,
          "pnl": -277780.0,
          "pnl_pct": -0.27820844099913866,
          "impact_bps": 7.5169,
          "phase": "training",
          "composite_score": 0.9511494252873564
        },
        {
          "code": "88970",
          "entry_date": "2008-08-05",
          "exit_date": "2008-11-06",
          "entry_price": 85.3,
          "exit_price": 58.3,
          "shares": 11723,
          "pnl": -316521.0,
          "pnl_pct": -0.3165298944900352,
          "impact_bps": 19.3721,
          "phase": "training",
          "composite_score": 0.9137931034482758
        },
        {
          "code": "33970",
          "entry_date": "2008-08-05",
          "exit_date": "2009-02-12",
          "entry_price": 191.7,
          "exit_price": 374.2,
          "shares": 5216,
          "pnl": 951920.0,
          "pnl_pct": 0.9520083463745437,
          "impact_bps": 11.9609,
          "phase": "training",
          "composite_score": 0.9827586206896551
        },
        {
          "code": "46890",
          "entry_date": "2008-08-05",
          "exit_date": "2009-02-12",
          "entry_price": 373.0,
          "exit_price": 266.3,
          "shares": 2680,
          "pnl": -285955.99999999994,
          "pnl_pct": -0.2860589812332439,
          "impact_bps": 8.0397,
          "phase": "training",
          "composite_score": 0.9367816091954023
        },
        {
          "code": "94330",
          "entry_date": "2008-08-05",
          "exit_date": "2009-02-12",
          "entry_price": 559.2,
          "exit_price": 409.2,
          "shares": 1788,
          "pnl": -268200.0000000001,
          "pnl_pct": -0.2682403433476396,
          "impact_bps": 6.7897,
          "phase": "training",
          "composite_score": 0.9252873563218391
        },
        {
          "code": "36200",
          "entry_date": "2008-08-05",
          "exit_date": "2009-02-12",
          "entry_price": 558.3,
          "exit_price": 922.5,
          "shares": 1791,
          "pnl": 652282.2000000001,
          "pnl_pct": 0.6523374529822676,
          "impact_bps": 19.5632,
          "phase": "training",
          "composite_score": 0.9224137931034483
        },
        {
          "code": "90200",
          "entry_date": "2008-08-05",
          "exit_date": "2009-02-12",
          "entry_price": 2903.3,
          "exit_price": 1933.3,
          "shares": 344,
          "pnl": -333680.00000000006,
          "pnl_pct": -0.3341025729342473,
          "impact_bps": 7.6064,
          "phase": "training",
          "composite_score": 0.8879310344827587
        },
        {
          "code": "90220",
          "entry_date": "2008-11-06",
          "exit_date": "2009-02-12",
          "entry_price": 1676.0,
          "exit_price": 1152.0,
          "shares": 262,
          "pnl": -137288.0,
          "pnl_pct": -0.31264916467780435,
          "impact_bps": 6.6629,
          "phase": "training",
          "composite_score": 0.9599723193473193
        },
        {
          "code": "67270",
          "entry_date": "2009-02-12",
          "exit_date": "2009-05-19",
          "entry_price": 169.5,
          "exit_price": 403.0,
          "shares": 5484,
          "pnl": 1280514.0,
          "pnl_pct": 1.3775811209439528,
          "impact_bps": 20.6551,
          "phase": "training",
          "composite_score": 0.9477332194158168
        },
        {
          "code": "94370",
          "entry_date": "2008-08-05",
          "exit_date": "2009-08-17",
          "entry_price": 1738.0,
          "exit_price": 1390.0,
          "shares": 548,
          "pnl": -190704.0,
          "pnl_pct": -0.20023014959723817,
          "impact_bps": 6.2997,
          "phase": "training",
          "composite_score": 0.8850574712643677
        },
        {
          "code": "30920",
          "entry_date": "2008-11-06",
          "exit_date": "2009-08-17",
          "entry_price": 26.7,
          "exit_price": 52.4,
          "shares": 16448,
          "pnl": 422713.6,
          "pnl_pct": 0.9625468164794007,
          "impact_bps": 7.8179,
          "phase": "training",
          "composite_score": 0.9808784965034965
        },
        {
          "code": "24130",
          "entry_date": "2008-11-06",
          "exit_date": "2009-11-19",
          "entry_price": 129.2,
          "exit_price": 115.5,
          "shares": 3399,
          "pnl": -46566.29999999996,
          "pnl_pct": -0.10603715170278627,
          "impact_bps": 6.875,
          "phase": "training",
          "composite_score": 0.9634081196581197
        },
        {
          "code": "49240",
          "entry_date": "2008-11-06",
          "exit_date": "2009-11-19",
          "entry_price": 840.0,
          "exit_price": 885.0,
          "shares": 522,
          "pnl": 23490.0,
          "pnl_pct": 0.0535714285714286,
          "impact_bps": 13.2268,
          "phase": "training",
          "composite_score": 0.9615384615384616
        },
        {
          "code": "87030",
          "entry_date": "2009-05-19",
          "exit_date": "2009-11-19",
          "entry_price": 273.5,
          "exit_price": 207.5,
          "shares": 530,
          "pnl": -34980.0,
          "pnl_pct": -0.24131627056672755,
          "impact_bps": 17.3079,
          "phase": "training",
          "composite_score": 0.9198813056379822
        },
        {
          "code": "21700",
          "entry_date": "2009-02-12",
          "exit_date": "2010-02-24",
          "entry_price": 60.6,
          "exit_price": 50.1,
          "shares": 15340,
          "pnl": -161070.0,
          "pnl_pct": -0.1732673267326733,
          "impact_bps": 22.4331,
          "phase": "training",
          "composite_score": 0.9836279169114113
        },
        {
          "code": "94330",
          "entry_date": "2009-02-12",
          "exit_date": "2010-02-24",
          "entry_price": 409.2,
          "exit_price": 393.8,
          "shares": 2271,
          "pnl": -34973.39999999995,
          "pnl_pct": -0.037634408602150504,
          "impact_bps": 6.7251,
          "phase": "training",
          "composite_score": 0.9592193090190634
        },
        {
          "code": "33970",
          "entry_date": "2009-02-12",
          "exit_date": "2010-02-24",
          "entry_price": 374.2,
          "exit_price": 408.8,
          "shares": 2484,
          "pnl": 85946.40000000005,
          "pnl_pct": 0.09246392303580975,
          "impact_bps": 11.7092,
          "phase": "training",
          "composite_score": 0.9542158380947295
        },
        {
          "code": "90220",
          "entry_date": "2009-02-12",
          "exit_date": "2010-02-24",
          "entry_price": 1152.0,
          "exit_price": 1328.0,
          "shares": 806,
          "pnl": 141856.0,
          "pnl_pct": 0.15277777777777768,
          "impact_bps": 7.426,
          "phase": "training",
          "composite_score": 0.9477866182517221
        },
        {
          "code": "36200",
          "entry_date": "2009-02-12",
          "exit_date": "2010-02-24",
          "entry_price": 922.5,
          "exit_price": 660.5,
          "shares": 1007,
          "pnl": -263834.0,
          "pnl_pct": -0.28401084010840105,
          "impact_bps": 19.0361,
          "phase": "training",
          "composite_score": 0.9426549901212153
        },
        {
          "code": "46890",
          "entry_date": "2009-02-12",
          "exit_date": "2010-02-24",
          "entry_price": 266.3,
          "exit_price": 324.5,
          "shares": 3490,
          "pnl": 203117.99999999997,
          "pnl_pct": 0.21855050694705214,
          "impact_bps": 7.9299,
          "phase": "training",
          "composite_score": 0.9377155977999679
        },
        {
          "code": "24500",
          "entry_date": "2009-02-12",
          "exit_date": "2010-02-24",
          "entry_price": 350.5,
          "exit_price": 398.0,
          "shares": 1665,
          "pnl": 79087.5,
          "pnl_pct": 0.13552068473609125,
          "impact_bps": 13.6171,
          "phase": "training",
          "composite_score": 0.9166283975009344
        },
        {
          "code": "21310",
          "entry_date": "2009-05-19",
          "exit_date": "2010-02-24",
          "entry_price": 606.0,
          "exit_price": 929.0,
          "shares": 1723,
          "pnl": 556529.0,
          "pnl_pct": 0.533003300330033,
          "impact_bps": 19.7923,
          "phase": "training",
          "composite_score": 0.93026706231454
        },
        {
          "code": "67270",
          "entry_date": "2009-05-19",
          "exit_date": "2010-05-31",
          "entry_price": 403.0,
          "exit_price": 341.8,
          "shares": 2591,
          "pnl": -158569.19999999998,
          "pnl_pct": -0.15186104218362284,
          "impact_bps": 21.6041,
          "phase": "training",
          "composite_score": 0.9406528189910979
        },
        {
          "code": "26950",
          "entry_date": "2009-08-17",
          "exit_date": "2010-08-27",
          "entry_price": 499.5,
          "exit_price": 732.5,
          "shares": 2519,
          "pnl": 586927.0,
          "pnl_pct": 0.4664664664664664,
          "impact_bps": 17.0874,
          "phase": "training",
          "composite_score": 0.9575558427845843
        },
        {
          "code": "30920",
          "entry_date": "2009-08-17",
          "exit_date": "2010-08-27",
          "entry_price": 52.4,
          "exit_price": 83.5,
          "shares": 6762,
          "pnl": 210298.2,
          "pnl_pct": 0.5935114503816794,
          "impact_bps": 9.7905,
          "phase": "training",
          "composite_score": 0.9544382953159418
        },
        {
          "code": "24130",
          "entry_date": "2009-11-19",
          "exit_date": "2010-12-01",
          "entry_price": 115.5,
          "exit_price": 175.0,
          "shares": 8086,
          "pnl": 481117.0,
          "pnl_pct": 0.5151515151515151,
          "impact_bps": 8.077,
          "phase": "training",
          "composite_score": 0.9666581711601827
        },
        {
          "code": "33970",
          "entry_date": "2010-02-24",
          "exit_date": "2010-12-01",
          "entry_price": 408.8,
          "exit_price": 282.5,
          "shares": 2920,
          "pnl": -368796.00000000006,
          "pnl_pct": -0.30895303326810175,
          "impact_bps": 12.6124,
          "phase": "training",
          "composite_score": 0.9642415029764614
        },
        {
          "code": "21310",
          "entry_date": "2010-02-24",
          "exit_date": "2010-12-01",
          "entry_price": 929.0,
          "exit_price": 734.0,
          "shares": 1285,
          "pnl": -250575.0,
          "pnl_pct": -0.20990312163616798,
          "impact_bps": 20.8272,
          "phase": "training",
          "composite_score": 0.942919298756622
        },
        {
          "code": "94330",
          "entry_date": "2010-02-24",
          "exit_date": "2011-03-07",
          "entry_price": 393.8,
          "exit_price": 445.0,
          "shares": 3031,
          "pnl": 155187.19999999995,
          "pnl_pct": 0.1300152361604876,
          "impact_bps": 6.9568,
          "phase": "training",
          "composite_score": 0.947952886348328
        },
        {
          "code": "46890",
          "entry_date": "2010-02-24",
          "exit_date": "2011-03-07",
          "entry_price": 324.5,
          "exit_price": 319.5,
          "shares": 3679,
          "pnl": -18395.0,
          "pnl_pct": -0.015408320493066285,
          "impact_bps": 8.3238,
          "phase": "training",
          "composite_score": 0.94178605887386
        },
        {
          "code": "24500",
          "entry_date": "2010-02-24",
          "exit_date": "2011-03-07",
          "entry_price": 398.0,
          "exit_price": 446.0,
          "shares": 2999,
          "pnl": 143952.0,
          "pnl_pct": 0.12060301507537696,
          "impact_bps": 14.7777,
          "phase": "training",
          "composite_score": 0.9339170959931551
        },
        {
          "code": "90220",
          "entry_date": "2010-02-24",
          "exit_date": "2011-03-07",
          "entry_price": 1328.0,
          "exit_price": 1460.0,
          "shares": 899,
          "pnl": 118668.0,
          "pnl_pct": 0.09939759036144569,
          "impact_bps": 7.7521,
          "phase": "training",
          "composite_score": 0.9296981667910651
        },
        {
          "code": "36200",
          "entry_date": "2010-02-24",
          "exit_date": "2011-03-07",
          "entry_price": 660.5,
          "exit_price": 860.0,
          "shares": 1001,
          "pnl": 199699.5,
          "pnl_pct": 0.3020439061317184,
          "impact_bps": 20.9283,
          "phase": "training",
          "composite_score": 0.9293659318053558
        },
        {
          "code": "30920",
          "entry_date": "2010-08-27",
          "exit_date": "2011-03-07",
          "entry_price": 83.5,
          "exit_price": 161.0,
          "shares": 13896,
          "pnl": 1076940.0,
          "pnl_pct": 0.9281437125748504,
          "impact_bps": 9.7461,
          "phase": "training",
          "composite_score": 0.959214501510574
        },
        {
          "code": "49240",
          "entry_date": "2010-05-31",
          "exit_date": "2011-06-09",
          "entry_price": 1141.5,
          "exit_price": 1845.0,
          "shares": 766,
          "pnl": 538881.0,
          "pnl_pct": 0.6162943495400788,
          "impact_bps": 18.9913,
          "phase": "training",
          "composite_score": 0.9382530120481928
        },
        {
          "code": "26950",
          "entry_date": "2010-08-27",
          "exit_date": "2011-06-09",
          "entry_price": 732.5,
          "exit_price": 585.0,
          "shares": 1686,
          "pnl": -248685.0,
          "pnl_pct": -0.20136518771331058,
          "impact_bps": 16.9751,
          "phase": "training",
          "composite_score": 0.9637462235649548
        },
        {
          "code": "21310",
          "entry_date": "2011-03-07",
          "exit_date": "2011-06-09",
          "entry_price": 692.0,
          "exit_price": 503.0,
          "shares": 2017,
          "pnl": -381213.0,
          "pnl_pct": -0.273121387283237,
          "impact_bps": 22.1292,
          "phase": "training",
          "composite_score": 0.9404761904761905
        },
        {
          "code": "36200",
          "entry_date": "2011-03-07",
          "exit_date": "2011-06-09",
          "entry_price": 860.0,
          "exit_price": 637.0,
          "shares": 1623,
          "pnl": -361929.0,
          "pnl_pct": -0.2593023255813953,
          "impact_bps": 22.2386,
          "phase": "training",
          "composite_score": 0.9181547619047619
        },
        {
          "code": "24130",
          "entry_date": "2010-12-01",
          "exit_date": "2011-09-07",
          "entry_price": 175.0,
          "exit_price": 277.1,
          "shares": 3513,
          "pnl": 358677.3000000001,
          "pnl_pct": 0.5834285714285716,
          "impact_bps": 7.2213,
          "phase": "training",
          "composite_score": 0.9635258358662614
        },
        {
          "code": "46890",
          "entry_date": "2011-03-07",
          "exit_date": "2011-09-07",
          "entry_price": 319.5,
          "exit_price": 238.8,
          "shares": 4369,
          "pnl": -352578.29999999993,
          "pnl_pct": -0.2525821596244131,
          "impact_bps": 8.5964,
          "phase": "training",
          "composite_score": 0.9449404761904762
        },
        {
          "code": "33970",
          "entry_date": "2010-12-01",
          "exit_date": "2011-12-12",
          "entry_price": 282.5,
          "exit_price": 374.5,
          "shares": 2176,
          "pnl": 200192.0,
          "pnl_pct": 0.3256637168141594,
          "impact_bps": 10.4463,
          "phase": "training",
          "composite_score": 0.9620060790273557
        },
        {
          "code": "34430",
          "entry_date": "2011-03-07",
          "exit_date": "2011-12-12",
          "entry_price": 498.0,
          "exit_price": 358.0,
          "shares": 2803,
          "pnl": -392420.0,
          "pnl_pct": -0.2811244979919679,
          "impact_bps": 20.7348,
          "phase": "training",
          "composite_score": 0.9419642857142857
        },
        {
          "code": "21700",
          "entry_date": "2011-03-07",
          "exit_date": "2012-03-14",
          "entry_price": 62.3,
          "exit_price": 61.6,
          "shares": 22409,
          "pnl": -15686.299999999905,
          "pnl_pct": -0.011235955056179692,
          "impact_bps": 26.4126,
          "phase": "training",
          "composite_score": 0.9776785714285714
        },
        {
          "code": "30920",
          "entry_date": "2011-03-07",
          "exit_date": "2012-03-14",
          "entry_price": 161.0,
          "exit_price": 151.4,
          "shares": 8671,
          "pnl": -83241.59999999995,
          "pnl_pct": -0.05962732919254654,
          "impact_bps": 10.0482,
          "phase": "training",
          "composite_score": 0.9747023809523809
        },
        {
          "code": "90220",
          "entry_date": "2011-03-07",
          "exit_date": "2012-03-14",
          "entry_price": 1460.0,
          "exit_price": 1360.0,
          "shares": 956,
          "pnl": -95600.0,
          "pnl_pct": -0.06849315068493156,
          "impact_bps": 7.9777,
          "phase": "training",
          "composite_score": 0.9107142857142857
        },
        {
          "code": "94330",
          "entry_date": "2011-03-07",
          "exit_date": "2012-03-14",
          "entry_price": 445.0,
          "exit_price": 456.7,
          "shares": 1101,
          "pnl": 12881.699999999988,
          "pnl_pct": 0.026292134831460645,
          "impact_bps": 7.1172,
          "phase": "training",
          "composite_score": 0.9002976190476191
        },
        {
          "code": "49240",
          "entry_date": "2011-06-09",
          "exit_date": "2012-06-15",
          "entry_price": 1845.0,
          "exit_price": 1334.0,
          "shares": 699,
          "pnl": -357189.0,
          "pnl_pct": -0.27696476964769645,
          "impact_bps": 19.1761,
          "phase": "training",
          "composite_score": 0.9430013846181511
        },
        {
          "code": "36200",
          "entry_date": "2011-06-09",
          "exit_date": "2012-06-15",
          "entry_price": 637.0,
          "exit_price": 799.0,
          "shares": 2025,
          "pnl": 328050.0,
          "pnl_pct": 0.2543171114599685,
          "impact_bps": 21.5636,
          "phase": "training",
          "composite_score": 0.9280403157648667
        },
        {
          "code": "88760",
          "entry_date": "2011-06-09",
          "exit_date": "2012-06-15",
          "entry_price": 159.1,
          "exit_price": 240.3,
          "shares": 8108,
          "pnl": 658369.6000000001,
          "pnl_pct": 0.5103708359522314,
          "impact_bps": 15.7614,
          "phase": "training",
          "composite_score": 0.9115103127079175
        },
        {
          "code": "88970",
          "entry_date": "2011-06-09",
          "exit_date": "2012-06-15",
          "entry_price": 128.5,
          "exit_price": 142.0,
          "shares": 4468,
          "pnl": 60318.0,
          "pnl_pct": 0.10505836575875493,
          "impact_bps": 21.3462,
          "phase": "training",
          "composite_score": 0.9099413785042527
        },
        {
          "code": "37560",
          "entry_date": "2012-03-14",
          "exit_date": "2012-06-15",
          "entry_price": 254.0,
          "exit_price": 195.0,
          "shares": 1085,
          "pnl": -64015.0,
          "pnl_pct": -0.23228346456692917,
          "impact_bps": 26.2012,
          "phase": "training",
          "composite_score": 0.8885269173370218
        },
        {
          "code": "24130",
          "entry_date": "2011-09-07",
          "exit_date": "2012-09-13",
          "entry_price": 277.1,
          "exit_price": 337.5,
          "shares": 4955,
          "pnl": 299281.9999999999,
          "pnl_pct": 0.21797185131721397,
          "impact_bps": 8.3298,
          "phase": "training",
          "composite_score": 0.9682730923694779
        },
        {
          "code": "46890",
          "entry_date": "2011-09-07",
          "exit_date": "2012-09-13",
          "entry_price": 238.8,
          "exit_price": 293.6,
          "shares": 2681,
          "pnl": 146918.80000000002,
          "pnl_pct": 0.22948073701842553,
          "impact_bps": 8.5663,
          "phase": "training",
          "composite_score": 0.9425337714494342
        },
        {
          "code": "33970",
          "entry_date": "2011-12-12",
          "exit_date": "2012-09-13",
          "entry_price": 374.5,
          "exit_price": 603.5,
          "shares": 3593,
          "pnl": 822797.0,
          "pnl_pct": 0.6114819759679573,
          "impact_bps": 13.0864,
          "phase": "training",
          "composite_score": 0.9515147062874774
        },
        {
          "code": "30480",
          "entry_date": "2011-12-12",
          "exit_date": "2012-12-14",
          "entry_price": 417.0,
          "exit_price": 407.5,
          "shares": 1154,
          "pnl": -10963.0,
          "pnl_pct": -0.0227817745803357,
          "impact_bps": 15.6267,
          "phase": "training",
          "composite_score": 0.9001276412088265
        },
        {
          "code": "36610",
          "entry_date": "2012-06-15",
          "exit_date": "2012-12-14",
          "entry_price": 57.8,
          "exit_price": 136.9,
          "shares": 24385,
          "pnl": 1928853.5000000002,
          "pnl_pct": 1.3685121107266438,
          "impact_bps": 18.2589,
          "phase": "training",
          "composite_score": 0.9396316383358206
        },
        {
          "code": "37560",
          "entry_date": "2012-06-15",
          "exit_date": "2012-12-14",
          "entry_price": 195.0,
          "exit_price": 314.5,
          "shares": 5514,
          "pnl": 658923.0,
          "pnl_pct": 0.6128205128205129,
          "impact_bps": 26.1918,
          "phase": "training",
          "composite_score": 0.9382029629090379
        },
        {
          "code": "21310",
          "entry_date": "2012-09-13",
          "exit_date": "2012-12-14",
          "entry_price": 490.0,
          "exit_price": 756.0,
          "shares": 2991,
          "pnl": 795606.0,
          "pnl_pct": 0.5428571428571429,
          "impact_bps": 23.1811,
          "phase": "training",
          "composite_score": 0.9098737291508376
        },
        {
          "code": "21700",
          "entry_date": "2012-03-14",
          "exit_date": "2013-03-25",
          "entry_price": 61.6,
          "exit_price": 106.4,
          "shares": 22900,
          "pnl": 1025920.0000000001,
          "pnl_pct": 0.7272727272727273,
          "impact_bps": 26.5253,
          "phase": "training",
          "composite_score": 0.9638372219997816
        },
        {
          "code": "94330",
          "entry_date": "2012-03-14",
          "exit_date": "2013-03-25",
          "entry_price": 456.7,
          "exit_price": 630.8,
          "shares": 3088,
          "pnl": 537620.7999999999,
          "pnl_pct": 0.3812130501423252,
          "impact_bps": 7.1283,
          "phase": "training",
          "composite_score": 0.9186701488734395
        },
        {
          "code": "90220",
          "entry_date": "2012-03-14",
          "exit_date": "2013-03-25",
          "entry_price": 1360.0,
          "exit_price": 1984.0,
          "shares": 1037,
          "pnl": 647088.0,
          "pnl_pct": 0.45882352941176463,
          "impact_bps": 7.9933,
          "phase": "training",
          "composite_score": 0.8990827357769446
        },
        {
          "code": "37560",
          "entry_date": "2012-12-14",
          "exit_date": "2013-03-25",
          "entry_price": 314.5,
          "exit_price": 581.5,
          "shares": 5843,
          "pnl": 1560081.0,
          "pnl_pct": 0.848966613672496,
          "impact_bps": 29.2347,
          "phase": "training",
          "composite_score": 0.9425981873111782
        },
        {
          "code": "49240",
          "entry_date": "2012-06-15",
          "exit_date": "2013-06-25",
          "entry_price": 1334.0,
          "exit_price": 1285.5,
          "shares": 1056,
          "pnl": -51216.0,
          "pnl_pct": -0.03635682158920539,
          "impact_bps": 19.8246,
          "phase": "training",
          "composite_score": 0.9456875841735521
        },
        {
          "code": "36200",
          "entry_date": "2012-06-15",
          "exit_date": "2013-06-25",
          "entry_price": 799.0,
          "exit_price": 2192.0,
          "shares": 1764,
          "pnl": 2457252.0,
          "pnl_pct": 1.7434292866082601,
          "impact_bps": 22.3216,
          "phase": "training",
          "composite_score": 0.9426800859025224
        },
        {
          "code": "24130",
          "entry_date": "2012-09-13",
          "exit_date": "2013-06-25",
          "entry_price": 337.5,
          "exit_price": 549.5,
          "shares": 4654,
          "pnl": 986648.0,
          "pnl_pct": 0.6281481481481481,
          "impact_bps": 8.5635,
          "phase": "training",
          "composite_score": 0.9684051521400919
        },
        {
          "code": "46890",
          "entry_date": "2012-09-13",
          "exit_date": "2013-06-25",
          "entry_price": 293.6,
          "exit_price": 469.5,
          "shares": 5350,
          "pnl": 941064.9999999999,
          "pnl_pct": 0.5991144414168936,
          "impact_bps": 8.8167,
          "phase": "training",
          "composite_score": 0.9473434277651145
        },
        {
          "code": "37560",
          "entry_date": "2013-03-25",
          "exit_date": "2013-06-25",
          "entry_price": 581.5,
          "exit_price": 342.5,
          "shares": 4171,
          "pnl": -996869.0,
          "pnl_pct": -0.41100601891659505,
          "impact_bps": 32.89,
          "phase": "training",
          "composite_score": 0.9363636363636364
        },
        {
          "code": "21310",
          "entry_date": "2012-12-14",
          "exit_date": "2013-09-25",
          "entry_price": 756.0,
          "exit_price": 1142.0,
          "shares": 2430,
          "pnl": 937980.0,
          "pnl_pct": 0.5105820105820107,
          "impact_bps": 24.6819,
          "phase": "training",
          "composite_score": 0.904833836858006
        },
        {
          "code": "21700",
          "entry_date": "2013-03-25",
          "exit_date": "2013-09-25",
          "entry_price": 106.4,
          "exit_price": 160.3,
          "shares": 22799,
          "pnl": 1228866.1,
          "pnl_pct": 0.506578947368421,
          "impact_bps": 33.3166,
          "phase": "training",
          "composite_score": 0.9757575757575758
        },
        {
          "code": "23840",
          "entry_date": "2012-12-14",
          "exit_date": "2013-12-26",
          "entry_price": 378.0,
          "exit_price": 512.0,
          "shares": 4861,
          "pnl": 651374.0,
          "pnl_pct": 0.3544973544973544,
          "impact_bps": 28.6522,
          "phase": "training",
          "composite_score": 0.9108761329305136
        },
        {
          "code": "66700",
          "entry_date": "2012-12-14",
          "exit_date": "2013-12-26",
          "entry_price": 81.0,
          "exit_price": 131.0,
          "shares": 22687,
          "pnl": 1134350.0,
          "pnl_pct": 0.617283950617284,
          "impact_bps": 22.9438,
          "phase": "training",
          "composite_score": 0.9033232628398791
        },
        {
          "code": "27720",
          "entry_date": "2012-12-14",
          "exit_date": "2013-12-26",
          "entry_price": 477.8,
          "exit_price": 522.8,
          "shares": 1056,
          "pnl": 47519.99999999994,
          "pnl_pct": 0.09418166596902466,
          "impact_bps": 19.3661,
          "phase": "training",
          "composite_score": 0.8836858006042296
        },
        {
          "code": "67270",
          "entry_date": "2013-03-25",
          "exit_date": "2013-12-26",
          "entry_price": 916.3,
          "exit_price": 674.0,
          "shares": 2647,
          "pnl": -641368.0999999999,
          "pnl_pct": -0.264433045945651,
          "impact_bps": 30.4258,
          "phase": "training",
          "composite_score": 0.9424242424242424
        },
        {
          "code": "94330",
          "entry_date": "2013-03-25",
          "exit_date": "2013-12-26",
          "entry_price": 630.8,
          "exit_price": 1073.3,
          "shares": 3845,
          "pnl": 1701412.5,
          "pnl_pct": 0.7014901712111605,
          "impact_bps": 7.7966,
          "phase": "training",
          "composite_score": 0.9257575757575758
        },
        {
          "code": "90220",
          "entry_date": "2013-03-25",
          "exit_date": "2014-04-03",
          "entry_price": 1984.0,
          "exit_price": 2426.0,
          "shares": 78,
          "pnl": 34476.0,
          "pnl_pct": 0.22278225806451624,
          "impact_bps": 8.9339,
          "phase": "training",
          "composite_score": 0.9030303030303031
        },
        {
          "code": "24130",
          "entry_date": "2013-06-25",
          "exit_date": "2014-04-03",
          "entry_price": 549.5,
          "exit_price": 837.5,
          "shares": 2522,
          "pnl": 726336.0,
          "pnl_pct": 0.5241128298453139,
          "impact_bps": 8.3454,
          "phase": "training",
          "composite_score": 0.9700598802395209
        },
        {
          "code": "37560",
          "entry_date": "2013-06-25",
          "exit_date": "2014-07-04",
          "entry_price": 342.5,
          "exit_price": 534.0,
          "shares": 4046,
          "pnl": 774809.0,
          "pnl_pct": 0.5591240875912409,
          "impact_bps": 26.0118,
          "phase": "training",
          "composite_score": 0.968562874251497
        },
        {
          "code": "49240",
          "entry_date": "2013-09-25",
          "exit_date": "2014-10-06",
          "entry_price": 1427.0,
          "exit_price": 1822.5,
          "shares": 1035,
          "pnl": 409342.5,
          "pnl_pct": 0.27715487035739317,
          "impact_bps": 20.1806,
          "phase": "training",
          "composite_score": 0.9799465240641712
        },
        {
          "code": "46890",
          "entry_date": "2013-09-25",
          "exit_date": "2014-10-06",
          "entry_price": 543.0,
          "exit_price": 413.0,
          "shares": 2720,
          "pnl": -353600.0,
          "pnl_pct": -0.23941068139963173,
          "impact_bps": 8.7003,
          "phase": "training",
          "composite_score": 0.9598930481283423
        },
        {
          "code": "42810",
          "entry_date": "2013-12-26",
          "exit_date": "2014-10-06",
          "entry_price": 576.0,
          "exit_price": 460.0,
          "shares": 5419,
          "pnl": -628604.0,
          "pnl_pct": -0.20138888888888884,
          "impact_bps": 28.9889,
          "phase": "training",
          "composite_score": 0.873935872510899
        },
        {
          "code": "24500",
          "entry_date": "2013-12-26",
          "exit_date": "2015-01-13",
          "entry_price": 1484.0,
          "exit_price": 1383.0,
          "shares": 2103,
          "pnl": -212403.0,
          "pnl_pct": -0.06805929919137466,
          "impact_bps": 20.8887,
          "phase": "training",
          "composite_score": 0.9511495522563922
        },
        {
          "code": "21240",
          "entry_date": "2013-12-26",
          "exit_date": "2015-01-13",
          "entry_price": 168.6,
          "exit_price": 203.8,
          "shares": 18516,
          "pnl": 651763.2000000003,
          "pnl_pct": 0.2087781731909848,
          "impact_bps": 32.2581,
          "phase": "training",
          "composite_score": 0.9157792800754094
        },
        {
          "code": "77160",
          "entry_date": "2013-12-26",
          "exit_date": "2015-01-13",
          "entry_price": 979.3,
          "exit_price": 1560.0,
          "shares": 3187,
          "pnl": 1850690.9000000001,
          "pnl_pct": 0.592974573675074,
          "impact_bps": 28.8552,
          "phase": "training",
          "composite_score": 0.9131833981383293
        },
        {
          "code": "21700",
          "entry_date": "2013-12-26",
          "exit_date": "2015-01-13",
          "entry_price": 176.6,
          "exit_price": 156.0,
          "shares": 17677,
          "pnl": -364146.1999999999,
          "pnl_pct": -0.11664779161947902,
          "impact_bps": 37.1721,
          "phase": "training",
          "composite_score": 0.8901997172145635
        },
        {
          "code": "88970",
          "entry_date": "2013-12-26",
          "exit_date": "2015-01-13",
          "entry_price": 337.0,
          "exit_price": 508.0,
          "shares": 9263,
          "pnl": 1583973.0,
          "pnl_pct": 0.5074183976261128,
          "impact_bps": 30.5556,
          "phase": "training",
          "composite_score": 0.8872945387062566
        },
        {
          "code": "48160",
          "entry_date": "2013-12-26",
          "exit_date": "2015-01-13",
          "entry_price": 169.1,
          "exit_price": 233.3,
          "shares": 18461,
          "pnl": 1185196.2000000004,
          "pnl_pct": 0.3796570076877588,
          "impact_bps": 17.7621,
          "phase": "training",
          "composite_score": 0.8834025568516555
        },
        {
          "code": "88760",
          "entry_date": "2013-12-26",
          "exit_date": "2015-01-13",
          "entry_price": 511.0,
          "exit_price": 842.0,
          "shares": 4665,
          "pnl": 1544115.0,
          "pnl_pct": 0.6477495107632094,
          "impact_bps": 21.818,
          "phase": "training",
          "composite_score": 0.8724593495934959
        },
        {
          "code": "94330",
          "entry_date": "2013-12-26",
          "exit_date": "2015-01-13",
          "entry_price": 1073.3,
          "exit_price": 1252.2,
          "shares": 111,
          "pnl": 19857.90000000001,
          "pnl_pct": 0.16668219509922677,
          "impact_bps": 8.1757,
          "phase": "training",
          "composite_score": 0.8575210616236597
        },
        {
          "code": "49750",
          "entry_date": "2014-07-04",
          "exit_date": "2015-01-13",
          "entry_price": 858.8,
          "exit_price": 1385.0,
          "shares": 119,
          "pnl": 62617.8,
          "pnl_pct": 0.612715416860736,
          "impact_bps": 28.5281,
          "phase": "training",
          "composite_score": 0.9158031088082902
        },
        {
          "code": "24130",
          "entry_date": "2014-04-03",
          "exit_date": "2015-04-13",
          "entry_price": 837.5,
          "exit_price": 1261.5,
          "shares": 2618,
          "pnl": 1110032.0,
          "pnl_pct": 0.5062686567164179,
          "impact_bps": 10.0559,
          "phase": "training",
          "composite_score": 0.9760141843971631
        },
        {
          "code": "90220",
          "entry_date": "2014-04-03",
          "exit_date": "2015-04-13",
          "entry_price": 2426.0,
          "exit_price": 4384.0,
          "shares": 45,
          "pnl": 88110.0,
          "pnl_pct": 0.8070898598516076,
          "impact_bps": 9.4832,
          "phase": "training",
          "composite_score": 0.8934574468085106
        },
        {
          "code": "99630",
          "entry_date": "2015-01-13",
          "exit_date": "2015-04-13",
          "entry_price": 1046.0,
          "exit_price": 506.0,
          "shares": 3742,
          "pnl": -2020680.0,
          "pnl_pct": -0.5162523900573615,
          "impact_bps": 35.9415,
          "phase": "training",
          "composite_score": 0.8576334498132305
        },
        {
          "code": "90900",
          "entry_date": "2014-07-04",
          "exit_date": "2015-07-15",
          "entry_price": 117.3,
          "exit_price": 215.9,
          "shares": 17549,
          "pnl": 1730331.4000000001,
          "pnl_pct": 0.8405797101449277,
          "impact_bps": 37.0714,
          "phase": "training",
          "composite_score": 0.9507772020725389
        },
        {
          "code": "97570",
          "entry_date": "2015-01-13",
          "exit_date": "2015-07-15",
          "entry_price": 259.2,
          "exit_price": 455.6,
          "shares": 15103,
          "pnl": 2966229.2000000007,
          "pnl_pct": 0.7577160493827162,
          "impact_bps": 32.7698,
          "phase": "training",
          "composite_score": 0.8628583095687566
        },
        {
          "code": "72030",
          "entry_date": "2014-10-06",
          "exit_date": "2015-10-19",
          "entry_price": 1276.6,
          "exit_price": 1471.2,
          "shares": 2754,
          "pnl": 535928.4000000004,
          "pnl_pct": 0.15243615854613823,
          "impact_bps": 6.8249,
          "phase": "training",
          "composite_score": 0.9051948051948051
        },
        {
          "code": "85240",
          "entry_date": "2014-10-06",
          "exit_date": "2015-10-19",
          "entry_price": 419.0,
          "exit_price": 457.0,
          "shares": 4518,
          "pnl": 171684.0,
          "pnl_pct": 0.09069212410501204,
          "impact_bps": 15.8544,
          "phase": "training",
          "composite_score": 0.8999999999999999
        },
        {
          "code": "49750",
          "entry_date": "2015-01-13",
          "exit_date": "2015-10-19",
          "entry_price": 1385.0,
          "exit_price": 1055.0,
          "shares": 2826,
          "pnl": -932580.0,
          "pnl_pct": -0.2382671480144405,
          "impact_bps": 30.2242,
          "phase": "training",
          "composite_score": 0.8912753879316115
        },
        {
          "code": "36610",
          "entry_date": "2015-04-13",
          "exit_date": "2015-10-19",
          "entry_price": 97.6,
          "exit_price": 77.4,
          "shares": 12629,
          "pnl": -255105.79999999984,
          "pnl_pct": -0.20696721311475397,
          "impact_bps": 27.7857,
          "phase": "training",
          "composite_score": 0.9087403598971722
        }
      ]
    },
    "validation": {
      "phase": "validation",
      "start_date": "2016-01-01",
      "end_date": "2020-12-31",
      "total_return": 1.289452,
      "annual_return": 0.180201,
      "sharpe_ratio": 0.9231,
      "sortino_ratio": 1.1516,
      "max_drawdown": 0.183691,
      "total_trades": 76,
      "win_rate": 0.5789,
      "profit_factor": 2.4751,
      "trades": [
        {
          "code": "77160",
          "entry_date": "2015-01-13",
          "exit_date": "2016-01-22",
          "entry_price": 1560.0,
          "exit_price": 1476.7,
          "shares": 2509,
          "pnl": -208999.6999999999,
          "pnl_pct": -0.05339743589743584,
          "impact_bps": 31.7493,
          "phase": "validation",
          "composite_score": 0.8901239774537761
        },
        {
          "code": "99840",
          "entry_date": "2015-01-13",
          "exit_date": "2016-01-22",
          "entry_price": 893.5,
          "exit_price": 612.9,
          "shares": 4381,
          "pnl": -1229308.6,
          "pnl_pct": -0.3140458869613878,
          "impact_bps": 5.8512,
          "phase": "validation",
          "composite_score": 0.8796106625965645
        },
        {
          "code": "94330",
          "entry_date": "2015-01-13",
          "exit_date": "2016-01-22",
          "entry_price": 1252.2,
          "exit_price": 1384.5,
          "shares": 3126,
          "pnl": 413569.7999999999,
          "pnl_pct": 0.10565404887398167,
          "impact_bps": 8.5595,
          "phase": "validation",
          "composite_score": 0.870663801528966
        },
        {
          "code": "83160",
          "entry_date": "2015-01-13",
          "exit_date": "2016-01-22",
          "entry_price": 1350.3,
          "exit_price": 1320.0,
          "shares": 2899,
          "pnl": -87839.69999999987,
          "pnl_pct": -0.022439457898244752,
          "impact_bps": 6.9614,
          "phase": "validation",
          "composite_score": 0.8539348783655327
        },
        {
          "code": "17230",
          "entry_date": "2015-01-13",
          "exit_date": "2016-01-22",
          "entry_price": 587.5,
          "exit_price": 617.0,
          "shares": 574,
          "pnl": 16933.0,
          "pnl_pct": 0.050212765957446726,
          "impact_bps": 28.4028,
          "phase": "validation",
          "composite_score": 0.8461595105166619
        },
        {
          "code": "90900",
          "entry_date": "2015-07-15",
          "exit_date": "2016-04-22",
          "entry_price": 215.9,
          "exit_price": 335.5,
          "shares": 20827,
          "pnl": 2490909.1999999997,
          "pnl_pct": 0.553960166743863,
          "impact_bps": 41.8841,
          "phase": "validation",
          "composite_score": 0.9183673469387754
        },
        {
          "code": "71730",
          "entry_date": "2015-07-15",
          "exit_date": "2016-04-22",
          "entry_price": 4045.0,
          "exit_price": 2950.0,
          "shares": 409,
          "pnl": -447855.0,
          "pnl_pct": -0.2707045735475896,
          "impact_bps": 24.1886,
          "phase": "validation",
          "composite_score": 0.9158163265306123
        },
        {
          "code": "43690",
          "entry_date": "2016-01-22",
          "exit_date": "2016-04-22",
          "entry_price": 142.3,
          "exit_price": 433.3,
          "shares": 13948,
          "pnl": 4058868.0,
          "pnl_pct": 2.044975404075896,
          "impact_bps": 13.8738,
          "phase": "validation",
          "composite_score": 0.875189393939394
        },
        {
          "code": "45680",
          "entry_date": "2015-07-15",
          "exit_date": "2016-07-27",
          "entry_price": 862.0,
          "exit_price": 834.0,
          "shares": 5216,
          "pnl": -146048.0,
          "pnl_pct": -0.0324825986078886,
          "impact_bps": 8.3878,
          "phase": "validation",
          "composite_score": 0.9349489795918368
        },
        {
          "code": "49750",
          "entry_date": "2015-10-19",
          "exit_date": "2016-07-27",
          "entry_price": 1055.0,
          "exit_price": 822.5,
          "shares": 3942,
          "pnl": -916515.0,
          "pnl_pct": -0.22037914691943128,
          "impact_bps": 31.0099,
          "phase": "validation",
          "composite_score": 0.90629722582038
        },
        {
          "code": "72030",
          "entry_date": "2015-10-19",
          "exit_date": "2016-07-27",
          "entry_price": 1471.2,
          "exit_price": 1173.2,
          "shares": 2827,
          "pnl": -842446.0,
          "pnl_pct": -0.2025557368134856,
          "impact_bps": 6.9859,
          "phase": "validation",
          "composite_score": 0.9053054835924006
        },
        {
          "code": "63230",
          "entry_date": "2016-04-22",
          "exit_date": "2016-07-27",
          "entry_price": 114.5,
          "exit_price": 190.0,
          "shares": 40139,
          "pnl": 3030494.5,
          "pnl_pct": 0.6593886462882097,
          "impact_bps": 12.7536,
          "phase": "validation",
          "composite_score": 0.9490861618798956
        },
        {
          "code": "90220",
          "entry_date": "2015-10-19",
          "exit_date": "2016-10-28",
          "entry_price": 4121.0,
          "exit_price": 3561.0,
          "shares": 425,
          "pnl": -238000.0,
          "pnl_pct": -0.13588934724581414,
          "impact_bps": 10.163,
          "phase": "validation",
          "composite_score": 0.8870223445595855
        },
        {
          "code": "27720",
          "entry_date": "2016-01-22",
          "exit_date": "2016-10-28",
          "entry_price": 1363.0,
          "exit_price": 3065.0,
          "shares": 1456,
          "pnl": 2478112.0,
          "pnl_pct": 1.2487160674981657,
          "impact_bps": 19.9363,
          "phase": "validation",
          "composite_score": 0.8959178841991342
        },
        {
          "code": "99840",
          "entry_date": "2016-01-22",
          "exit_date": "2017-02-02",
          "entry_price": 612.9,
          "exit_price": 1085.8,
          "shares": 3238,
          "pnl": 1531250.2,
          "pnl_pct": 0.7715777451460271,
          "impact_bps": 5.6048,
          "phase": "validation",
          "composite_score": 0.946685606060606
        },
        {
          "code": "49750",
          "entry_date": "2016-07-27",
          "exit_date": "2017-02-02",
          "entry_price": 822.5,
          "exit_price": 1490.0,
          "shares": 5764,
          "pnl": 3847470.0,
          "pnl_pct": 0.8115501519756838,
          "impact_bps": 32.7905,
          "phase": "validation",
          "composite_score": 0.9263565891472868
        },
        {
          "code": "71730",
          "entry_date": "2016-04-22",
          "exit_date": "2017-05-08",
          "entry_price": 2950.0,
          "exit_price": 3440.0,
          "shares": 1557,
          "pnl": 762930.0,
          "pnl_pct": 0.16610169491525428,
          "impact_bps": 24.4016,
          "phase": "validation",
          "composite_score": 0.9321148825065274
        },
        {
          "code": "90900",
          "entry_date": "2016-04-22",
          "exit_date": "2017-05-08",
          "entry_price": 335.5,
          "exit_price": 346.1,
          "shares": 13698,
          "pnl": 145198.8000000003,
          "pnl_pct": 0.03159463487332337,
          "impact_bps": 42.2941,
          "phase": "validation",
          "composite_score": 0.9125326370757181
        },
        {
          "code": "45950",
          "entry_date": "2016-04-22",
          "exit_date": "2017-05-08",
          "entry_price": 309.9,
          "exit_price": 583.8,
          "shares": 14830,
          "pnl": 4061936.9999999995,
          "pnl_pct": 0.8838334946757018,
          "impact_bps": 43.9079,
          "phase": "validation",
          "composite_score": 0.8890339425587468
        },
        {
          "code": "36610",
          "entry_date": "2016-04-22",
          "exit_date": "2017-05-08",
          "entry_price": 70.3,
          "exit_price": 105.6,
          "shares": 65376,
          "pnl": 2307772.8,
          "pnl_pct": 0.5021337126600285,
          "impact_bps": 29.0991,
          "phase": "validation",
          "composite_score": 0.8877284595300261
        },
        {
          "code": "69880",
          "entry_date": "2016-04-22",
          "exit_date": "2017-05-08",
          "entry_price": 1280.6,
          "exit_price": 1847.6,
          "shares": 222,
          "pnl": 125874.0,
          "pnl_pct": 0.44276120568483535,
          "impact_bps": 10.5445,
          "phase": "validation",
          "composite_score": 0.8746736292428199
        },
        {
          "code": "73120",
          "entry_date": "2017-02-02",
          "exit_date": "2017-05-08",
          "entry_price": 550.0,
          "exit_price": 416.0,
          "shares": 10879,
          "pnl": -1457786.0,
          "pnl_pct": -0.24363636363636365,
          "impact_bps": 25.2327,
          "phase": "validation",
          "composite_score": 0.925
        },
        {
          "code": "63230",
          "entry_date": "2016-07-27",
          "exit_date": "2017-08-04",
          "entry_price": 190.0,
          "exit_price": 242.6,
          "shares": 24953,
          "pnl": 1312527.7999999998,
          "pnl_pct": 0.2768421052631578,
          "impact_bps": 12.8762,
          "phase": "validation",
          "composite_score": 0.9289405684754521
        },
        {
          "code": "72030",
          "entry_date": "2016-07-27",
          "exit_date": "2017-08-04",
          "entry_price": 1173.2,
          "exit_price": 1243.2,
          "shares": 4041,
          "pnl": 282870.0,
          "pnl_pct": 0.059665871121718395,
          "impact_bps": 7.1213,
          "phase": "validation",
          "composite_score": 0.9018087855297158
        },
        {
          "code": "46260",
          "entry_date": "2016-07-27",
          "exit_date": "2017-08-04",
          "entry_price": 873.8,
          "exit_price": 1345.0,
          "shares": 4705,
          "pnl": 2216996.0,
          "pnl_pct": 0.5392538338292516,
          "impact_bps": 19.5672,
          "phase": "validation",
          "composite_score": 0.8798449612403101
        },
        {
          "code": "46850",
          "entry_date": "2016-07-27",
          "exit_date": "2017-08-04",
          "entry_price": 389.0,
          "exit_price": 510.0,
          "shares": 529,
          "pnl": 64009.0,
          "pnl_pct": 0.31105398457583555,
          "impact_bps": 45.5579,
          "phase": "validation",
          "composite_score": 0.8772609819121447
        },
        {
          "code": "49750",
          "entry_date": "2017-02-02",
          "exit_date": "2017-08-04",
          "entry_price": 1490.0,
          "exit_price": 2245.0,
          "shares": 196,
          "pnl": 147980.0,
          "pnl_pct": 0.5067114093959733,
          "impact_bps": 36.2642,
          "phase": "validation",
          "composite_score": 0.8802631578947369
        },
        {
          "code": "36610",
          "entry_date": "2017-05-08",
          "exit_date": "2017-08-04",
          "entry_price": 105.6,
          "exit_price": 222.8,
          "shares": 2255,
          "pnl": 264286.00000000006,
          "pnl_pct": 1.1098484848484849,
          "impact_bps": 33.4928,
          "phase": "validation",
          "composite_score": 0.8191489361702128
        },
        {
          "code": "90220",
          "entry_date": "2016-10-28",
          "exit_date": "2017-11-07",
          "entry_price": 3561.0,
          "exit_price": 4202.0,
          "shares": 1472,
          "pnl": 943552.0,
          "pnl_pct": 0.18000561639988777,
          "impact_bps": 10.8038,
          "phase": "validation",
          "composite_score": 0.921259842519685
        },
        {
          "code": "32310",
          "entry_date": "2016-10-28",
          "exit_date": "2017-11-07",
          "entry_price": 358.4,
          "exit_price": 498.6,
          "shares": 1975,
          "pnl": 276895.0000000001,
          "pnl_pct": 0.3911830357142858,
          "impact_bps": 16.5414,
          "phase": "validation",
          "composite_score": 0.8753280839895012
        },
        {
          "code": "90900",
          "entry_date": "2017-05-08",
          "exit_date": "2017-11-07",
          "entry_price": 346.1,
          "exit_price": 572.0,
          "shares": 18490,
          "pnl": 4176890.9999999995,
          "pnl_pct": 0.652701531349321,
          "impact_bps": 49.1007,
          "phase": "validation",
          "composite_score": 0.9375
        },
        {
          "code": "99840",
          "entry_date": "2017-02-02",
          "exit_date": "2018-02-09",
          "entry_price": 1085.8,
          "exit_price": 1101.0,
          "shares": 5388,
          "pnl": 81897.60000000024,
          "pnl_pct": 0.013998894824092778,
          "impact_bps": 6.0537,
          "phase": "validation",
          "composite_score": 0.8828947368421052
        },
        {
          "code": "96970",
          "entry_date": "2017-05-08",
          "exit_date": "2018-02-09",
          "entry_price": 311.0,
          "exit_price": 493.1,
          "shares": 20577,
          "pnl": 3747071.7000000007,
          "pnl_pct": 0.5855305466237943,
          "impact_bps": 12.3458,
          "phase": "validation",
          "composite_score": 0.8962765957446809
        },
        {
          "code": "45950",
          "entry_date": "2017-05-08",
          "exit_date": "2018-02-09",
          "entry_price": 583.8,
          "exit_price": 1255.0,
          "shares": 10961,
          "pnl": 7357023.2,
          "pnl_pct": 1.1497088043850634,
          "impact_bps": 51.0099,
          "phase": "validation",
          "composite_score": 0.8577127659574468
        },
        {
          "code": "34430",
          "entry_date": "2017-08-04",
          "exit_date": "2018-02-09",
          "entry_price": 2703.3,
          "exit_price": 1746.7,
          "shares": 2643,
          "pnl": -2528293.8000000003,
          "pnl_pct": -0.35386379610106167,
          "impact_bps": 40.939,
          "phase": "validation",
          "composite_score": 0.9266666666666666
        },
        {
          "code": "50210",
          "entry_date": "2017-08-04",
          "exit_date": "2018-02-09",
          "entry_price": 957.0,
          "exit_price": 1857.5,
          "shares": 215,
          "pnl": 193607.5,
          "pnl_pct": 0.9409613375130617,
          "impact_bps": 21.1253,
          "phase": "validation",
          "composite_score": 0.9053333333333333
        },
        {
          "code": "90900",
          "entry_date": "2017-11-07",
          "exit_date": "2018-02-09",
          "entry_price": 572.0,
          "exit_price": 932.5,
          "shares": 13486,
          "pnl": 4861703.0,
          "pnl_pct": 0.6302447552447552,
          "impact_bps": 53.4785,
          "phase": "validation",
          "composite_score": 0.896
        },
        {
          "code": "88760",
          "entry_date": "2017-05-08",
          "exit_date": "2018-05-16",
          "entry_price": 2001.0,
          "exit_price": 2866.0,
          "shares": 3198,
          "pnl": 2766270.0,
          "pnl_pct": 0.4322838580709645,
          "impact_bps": 29.1768,
          "phase": "validation",
          "composite_score": 0.8297872340425532
        },
        {
          "code": "95190",
          "entry_date": "2017-05-08",
          "exit_date": "2018-05-16",
          "entry_price": 325.5,
          "exit_price": 561.0,
          "shares": 14631,
          "pnl": 3445600.5,
          "pnl_pct": 0.7235023041474655,
          "impact_bps": 37.4143,
          "phase": "validation",
          "composite_score": 0.8271276595744681
        },
        {
          "code": "63230",
          "entry_date": "2017-08-04",
          "exit_date": "2018-08-14",
          "entry_price": 242.6,
          "exit_price": 215.6,
          "shares": 29457,
          "pnl": -795339.0,
          "pnl_pct": -0.11129431162407255,
          "impact_bps": 14.689,
          "phase": "validation",
          "composite_score": 0.94
        },
        {
          "code": "48160",
          "entry_date": "2017-08-04",
          "exit_date": "2018-08-14",
          "entry_price": 631.3,
          "exit_price": 760.0,
          "shares": 6529,
          "pnl": 840282.3000000003,
          "pnl_pct": 0.20386504039284037,
          "impact_bps": 24.3953,
          "phase": "validation",
          "composite_score": 0.9239999999999999
        },
        {
          "code": "90220",
          "entry_date": "2017-11-07",
          "exit_date": "2018-11-14",
          "entry_price": 4202.0,
          "exit_price": 4316.0,
          "shares": 1835,
          "pnl": 209190.0,
          "pnl_pct": 0.027129938124702546,
          "impact_bps": 12.0507,
          "phase": "validation",
          "composite_score": 0.9199999999999999
        },
        {
          "code": "86000",
          "entry_date": "2017-11-07",
          "exit_date": "2018-11-14",
          "entry_price": 531.0,
          "exit_price": 463.0,
          "shares": 4174,
          "pnl": -283832.0,
          "pnl_pct": -0.128060263653484,
          "impact_bps": 38.7899,
          "phase": "validation",
          "composite_score": 0.8746666666666667
        },
        {
          "code": "72030",
          "entry_date": "2017-11-07",
          "exit_date": "2018-11-14",
          "entry_price": 1436.6,
          "exit_price": 1333.4,
          "shares": 77,
          "pnl": -7946.399999999986,
          "pnl_pct": -0.07183628010580523,
          "impact_bps": 7.7108,
          "phase": "validation",
          "composite_score": 0.8613333333333333
        },
        {
          "code": "69880",
          "entry_date": "2018-05-16",
          "exit_date": "2018-11-14",
          "entry_price": 1691.8,
          "exit_price": 1229.2,
          "shares": 5506,
          "pnl": -2547075.5999999996,
          "pnl_pct": -0.27343657642747365,
          "impact_bps": 12.9192,
          "phase": "validation",
          "composite_score": 0.8499758291339505
        },
        {
          "code": "34860",
          "entry_date": "2018-08-14",
          "exit_date": "2018-11-14",
          "entry_price": 750.0,
          "exit_price": 473.0,
          "shares": 2724,
          "pnl": -754548.0,
          "pnl_pct": -0.3693333333333333,
          "impact_bps": 50.8032,
          "phase": "validation",
          "composite_score": 0.8851351351351351
        },
        {
          "code": "99840",
          "entry_date": "2018-02-09",
          "exit_date": "2019-02-21",
          "entry_price": 1101.0,
          "exit_price": 1278.8,
          "shares": 7987,
          "pnl": 1420088.5999999996,
          "pnl_pct": 0.16148955495004547,
          "impact_bps": 6.2791,
          "phase": "validation",
          "composite_score": 0.9624664879356568
        },
        {
          "code": "34430",
          "entry_date": "2018-02-09",
          "exit_date": "2019-02-21",
          "entry_price": 1746.7,
          "exit_price": 2280.0,
          "shares": 5034,
          "pnl": 2684632.1999999997,
          "pnl_pct": 0.30531860079006123,
          "impact_bps": 44.9209,
          "phase": "validation",
          "composite_score": 0.9504021447721179
        },
        {
          "code": "39970",
          "entry_date": "2018-05-16",
          "exit_date": "2019-02-21",
          "entry_price": 285.8,
          "exit_price": 150.6,
          "shares": 32594,
          "pnl": -4406708.800000001,
          "pnl_pct": -0.4730580825752275,
          "impact_bps": 36.2449,
          "phase": "validation",
          "composite_score": 0.8878984530645728
        },
        {
          "code": "50210",
          "entry_date": "2018-05-16",
          "exit_date": "2019-02-21",
          "entry_price": 2030.0,
          "exit_price": 1192.5,
          "shares": 4588,
          "pnl": -3842450.0,
          "pnl_pct": -0.4125615763546798,
          "impact_bps": 23.4374,
          "phase": "validation",
          "composite_score": 0.8507632134067737
        },
        {
          "code": "63230",
          "entry_date": "2018-08-14",
          "exit_date": "2019-02-21",
          "entry_price": 215.6,
          "exit_price": 171.9,
          "shares": 42652,
          "pnl": -1863892.3999999994,
          "pnl_pct": -0.20269016697588127,
          "impact_bps": 16.0047,
          "phase": "validation",
          "composite_score": 0.9054054054054055
        },
        {
          "code": "72670",
          "entry_date": "2018-05-16",
          "exit_date": "2019-05-30",
          "entry_price": 1213.3,
          "exit_price": 923.0,
          "shares": 7677,
          "pnl": -2228633.0999999996,
          "pnl_pct": -0.23926481496744412,
          "impact_bps": 10.3483,
          "phase": "validation",
          "composite_score": 0.8865837044415799
        },
        {
          "code": "67580",
          "entry_date": "2018-05-16",
          "exit_date": "2019-05-30",
          "entry_price": 1055.4,
          "exit_price": 1067.2,
          "shares": 8826,
          "pnl": 104146.7999999996,
          "pnl_pct": 0.011180595035057861,
          "impact_bps": 8.2033,
          "phase": "validation",
          "composite_score": 0.8525394058361655
        },
        {
          "code": "72690",
          "entry_date": "2018-05-16",
          "exit_date": "2019-05-30",
          "entry_price": 1543.5,
          "exit_price": 1331.3,
          "shares": 397,
          "pnl": -84243.40000000002,
          "pnl_pct": -0.1374797538062844,
          "impact_bps": 11.5397,
          "phase": "validation",
          "composite_score": 0.8470716629555841
        },
        {
          "code": "64250",
          "entry_date": "2018-08-14",
          "exit_date": "2019-08-29",
          "entry_price": 3870.0,
          "exit_price": 3100.0,
          "shares": 26,
          "pnl": -20020.0,
          "pnl_pct": -0.1989664082687338,
          "impact_bps": 48.594,
          "phase": "validation",
          "composite_score": 0.8445945945945946
        },
        {
          "code": "39970",
          "entry_date": "2019-02-21",
          "exit_date": "2019-08-29",
          "entry_price": 150.6,
          "exit_price": 110.1,
          "shares": 26415,
          "pnl": -1069807.5,
          "pnl_pct": -0.2689243027888446,
          "impact_bps": 25.3163,
          "phase": "validation",
          "composite_score": 0.9285714285714286
        },
        {
          "code": "50210",
          "entry_date": "2019-02-21",
          "exit_date": "2019-08-29",
          "entry_price": 1192.5,
          "exit_price": 937.0,
          "shares": 3335,
          "pnl": -852092.5,
          "pnl_pct": -0.21425576519916145,
          "impact_bps": 16.9941,
          "phase": "validation",
          "composite_score": 0.8901098901098901
        },
        {
          "code": "61660",
          "entry_date": "2019-05-30",
          "exit_date": "2019-08-29",
          "entry_price": 577.0,
          "exit_price": 425.0,
          "shares": 6815,
          "pnl": -1035880.0,
          "pnl_pct": -0.2634315424610052,
          "impact_bps": 26.775,
          "phase": "validation",
          "composite_score": 0.8785671887128441
        },
        {
          "code": "63230",
          "entry_date": "2019-02-21",
          "exit_date": "2019-12-03",
          "entry_price": 171.9,
          "exit_price": 393.0,
          "shares": 23142,
          "pnl": 5116696.2,
          "pnl_pct": 1.2862129144851657,
          "impact_bps": 12.2088,
          "phase": "validation",
          "composite_score": 0.9024725274725275
        },
        {
          "code": "61660",
          "entry_date": "2019-08-29",
          "exit_date": "2019-12-03",
          "entry_price": 425.0,
          "exit_price": 880.0,
          "shares": 9032,
          "pnl": 4109560.0,
          "pnl_pct": 1.0705882352941178,
          "impact_bps": 26.5109,
          "phase": "validation",
          "composite_score": 0.9001115727916282
        },
        {
          "code": "99840",
          "entry_date": "2019-02-21",
          "exit_date": "2020-03-10",
          "entry_price": 1278.8,
          "exit_price": 1097.0,
          "shares": 3110,
          "pnl": -565397.9999999999,
          "pnl_pct": -0.1421645292461683,
          "impact_bps": 5.8581,
          "phase": "validation",
          "composite_score": 0.907967032967033
        },
        {
          "code": "72030",
          "entry_date": "2019-02-21",
          "exit_date": "2020-03-10",
          "entry_price": 1346.2,
          "exit_price": 1320.0,
          "shares": 2955,
          "pnl": -77421.00000000013,
          "pnl_pct": -0.019462189867776036,
          "impact_bps": 6.9418,
          "phase": "validation",
          "composite_score": 0.8763736263736264
        },
        {
          "code": "39970",
          "entry_date": "2019-08-29",
          "exit_date": "2020-03-10",
          "entry_price": 110.1,
          "exit_price": 59.5,
          "shares": 34867,
          "pnl": -1764270.1999999997,
          "pnl_pct": -0.45958219800181654,
          "impact_bps": 24.9537,
          "phase": "validation",
          "composite_score": 0.9375307787011389
        },
        {
          "code": "50210",
          "entry_date": "2019-08-29",
          "exit_date": "2020-03-10",
          "entry_price": 937.0,
          "exit_price": 727.5,
          "shares": 4097,
          "pnl": -858321.5,
          "pnl_pct": -0.2235859124866596,
          "impact_bps": 16.7803,
          "phase": "validation",
          "composite_score": 0.8488573407202216
        },
        {
          "code": "63230",
          "entry_date": "2019-12-03",
          "exit_date": "2020-03-10",
          "entry_price": 393.0,
          "exit_price": 311.5,
          "shares": 22660,
          "pnl": -1846790.0,
          "pnl_pct": -0.20737913486005088,
          "impact_bps": 15.8279,
          "phase": "validation",
          "composite_score": 0.9060773480662984
        },
        {
          "code": "34430",
          "entry_date": "2019-12-03",
          "exit_date": "2020-03-10",
          "entry_price": 2260.0,
          "exit_price": 1740.0,
          "shares": 3940,
          "pnl": -2048800.0,
          "pnl_pct": -0.23008849557522126,
          "impact_bps": 45.1755,
          "phase": "validation",
          "composite_score": 0.8480662983425414
        },
        {
          "code": "61660",
          "entry_date": "2019-12-03",
          "exit_date": "2020-03-10",
          "entry_price": 880.0,
          "exit_price": 696.0,
          "shares": 10120,
          "pnl": -1862080.0,
          "pnl_pct": -0.2090909090909091,
          "impact_bps": 37.9272,
          "phase": "validation",
          "composite_score": 0.8466850828729282
        },
        {
          "code": "67580",
          "entry_date": "2019-05-30",
          "exit_date": "2020-06-12",
          "entry_price": 1067.2,
          "exit_price": 1480.8,
          "shares": 3685,
          "pnl": 1524115.9999999998,
          "pnl_pct": 0.38755622188905536,
          "impact_bps": 7.0745,
          "phase": "validation",
          "composite_score": 0.901990776676864
        },
        {
          "code": "18520",
          "entry_date": "2019-05-30",
          "exit_date": "2020-06-12",
          "entry_price": 357.0,
          "exit_price": 422.0,
          "shares": 11015,
          "pnl": 715975.0,
          "pnl_pct": 0.18207282913165268,
          "impact_bps": 31.8402,
          "phase": "validation",
          "composite_score": 0.8663797695691217
        },
        {
          "code": "63230",
          "entry_date": "2020-03-10",
          "exit_date": "2020-06-12",
          "entry_price": 311.5,
          "exit_price": 521.0,
          "shares": 11719,
          "pnl": 2455130.5,
          "pnl_pct": 0.6725521669341894,
          "impact_bps": 11.9029,
          "phase": "validation",
          "composite_score": 0.9027777777777778
        },
        {
          "code": "90220",
          "entry_date": "2019-08-29",
          "exit_date": "2020-09-14",
          "entry_price": 4183.0,
          "exit_price": 3426.0,
          "shares": 917,
          "pnl": -694169.0,
          "pnl_pct": -0.18097059526655512,
          "impact_bps": 9.9584,
          "phase": "validation",
          "composite_score": 0.861372730070791
        },
        {
          "code": "79740",
          "entry_date": "2019-12-03",
          "exit_date": "2020-12-16",
          "entry_price": 4439.0,
          "exit_price": 6341.0,
          "shares": 2006,
          "pnl": 3815412.0,
          "pnl_pct": 0.4284748817301194,
          "impact_bps": 8.038,
          "phase": "validation",
          "composite_score": 0.8522099447513812
        },
        {
          "code": "80880",
          "entry_date": "2019-12-03",
          "exit_date": "2020-12-16",
          "entry_price": 911.3,
          "exit_price": 1510.0,
          "shares": 9772,
          "pnl": 5850496.4,
          "pnl_pct": 0.6569735542631407,
          "impact_bps": 25.3957,
          "phase": "validation",
          "composite_score": 0.839779005524862
        },
        {
          "code": "48160",
          "entry_date": "2019-12-03",
          "exit_date": "2020-12-16",
          "entry_price": 1020.0,
          "exit_price": 1458.0,
          "shares": 8331,
          "pnl": 3648978.0,
          "pnl_pct": 0.4294117647058824,
          "impact_bps": 26.6784,
          "phase": "validation",
          "composite_score": 0.8149171270718232
        },
        {
          "code": "34860",
          "entry_date": "2019-12-03",
          "exit_date": "2020-12-16",
          "entry_price": 334.0,
          "exit_price": 460.5,
          "shares": 1273,
          "pnl": 161034.5,
          "pnl_pct": 0.37874251497005984,
          "impact_bps": 50.0649,
          "phase": "validation",
          "composite_score": 0.7997237569060773
        },
        {
          "code": "99840",
          "entry_date": "2020-03-10",
          "exit_date": "2020-12-16",
          "entry_price": 1097.0,
          "exit_price": 2007.5,
          "shares": 3327,
          "pnl": 3029233.5,
          "pnl_pct": 0.8299908842297175,
          "impact_bps": 5.8218,
          "phase": "validation",
          "composite_score": 0.925
        }
      ]
    },
    "out_of_sample": {
      "phase": "out_of_sample",
      "start_date": "2021-01-01",
      "end_date": "2026-12-31",
      "total_return": 1.334624,
      "annual_return": 0.151891,
      "sharpe_ratio": 0.7442,
      "sortino_ratio": 0.9301,
      "max_drawdown": 0.020925,
      "total_trades": 67,
      "win_rate": 0.7015,
      "profit_factor": 3.3048,
      "trades": [
        {
          "code": "46850",
          "entry_date": "2020-06-12",
          "exit_date": "2021-06-23",
          "entry_price": 788.0,
          "exit_price": 1011.0,
          "shares": 5176,
          "pnl": 1154248.0,
          "pnl_pct": 0.28299492385786795,
          "impact_bps": 42.5831,
          "phase": "out_of_sample",
          "composite_score": 0.9339887640449438
        },
        {
          "code": "63230",
          "entry_date": "2020-06-12",
          "exit_date": "2021-06-23",
          "entry_price": 521.0,
          "exit_price": 998.0,
          "shares": 7829,
          "pnl": 3734433.0,
          "pnl_pct": 0.9155470249520155,
          "impact_bps": 12.3004,
          "phase": "out_of_sample",
          "composite_score": 0.896067415730337
        },
        {
          "code": "18520",
          "entry_date": "2020-06-12",
          "exit_date": "2021-06-23",
          "entry_price": 422.0,
          "exit_price": 450.0,
          "shares": 9665,
          "pnl": 270620.0,
          "pnl_pct": 0.06635071090047395,
          "impact_bps": 32.3407,
          "phase": "out_of_sample",
          "composite_score": 0.8792134831460674
        },
        {
          "code": "34430",
          "entry_date": "2020-09-14",
          "exit_date": "2021-06-23",
          "entry_price": 1696.7,
          "exit_price": 1140.0,
          "shares": 2603,
          "pnl": -1449090.1,
          "pnl_pct": -0.32810750279955214,
          "impact_bps": 33.1699,
          "phase": "out_of_sample",
          "composite_score": 0.8742937853107344
        },
        {
          "code": "17200",
          "entry_date": "2020-12-16",
          "exit_date": "2021-06-23",
          "entry_price": 509.0,
          "exit_price": 781.0,
          "shares": 14352,
          "pnl": 3903744.0,
          "pnl_pct": 0.5343811394891944,
          "impact_bps": 44.5921,
          "phase": "out_of_sample",
          "composite_score": 0.8198847262247839
        },
        {
          "code": "91070",
          "entry_date": "2021-06-23",
          "exit_date": "2021-09-27",
          "entry_price": 432.2,
          "exit_price": 868.9,
          "shares": 26223,
          "pnl": 11451584.1,
          "pnl_pct": 1.0104118463674223,
          "impact_bps": 13.965,
          "phase": "out_of_sample",
          "composite_score": 0.9738372093023255
        },
        {
          "code": "90220",
          "entry_date": "2020-12-16",
          "exit_date": "2021-12-27",
          "entry_price": 2871.0,
          "exit_price": 3072.0,
          "shares": 3381,
          "pnl": 679581.0,
          "pnl_pct": 0.07001044932079425,
          "impact_bps": 12.918,
          "phase": "out_of_sample",
          "composite_score": 0.8602305475504323
        },
        {
          "code": "63680",
          "entry_date": "2020-12-16",
          "exit_date": "2021-12-27",
          "entry_price": 1547.5,
          "exit_price": 1957.5,
          "shares": 6273,
          "pnl": 2571930.0,
          "pnl_pct": 0.2649434571890146,
          "impact_bps": 18.8181,
          "phase": "out_of_sample",
          "composite_score": 0.8544668587896254
        },
        {
          "code": "79740",
          "entry_date": "2020-12-16",
          "exit_date": "2021-12-27",
          "entry_price": 6341.0,
          "exit_price": 5540.0,
          "shares": 1530,
          "pnl": -1225530.0,
          "pnl_pct": -0.12632076959470118,
          "impact_bps": 8.1729,
          "phase": "out_of_sample",
          "composite_score": 0.8501440922190202
        },
        {
          "code": "72030",
          "entry_date": "2020-12-16",
          "exit_date": "2021-12-27",
          "entry_price": 1596.0,
          "exit_price": 2108.0,
          "shares": 6082,
          "pnl": 3113984.0,
          "pnl_pct": 0.3208020050125313,
          "impact_bps": 8.0437,
          "phase": "out_of_sample",
          "composite_score": 0.8342939481268011
        },
        {
          "code": "93020",
          "entry_date": "2020-12-16",
          "exit_date": "2021-12-27",
          "entry_price": 764.7,
          "exit_price": 800.7,
          "shares": 12694,
          "pnl": 456984.0,
          "pnl_pct": 0.04707728520988619,
          "impact_bps": 36.5907,
          "phase": "out_of_sample",
          "composite_score": 0.829971181556196
        },
        {
          "code": "32310",
          "entry_date": "2020-12-16",
          "exit_date": "2021-12-27",
          "entry_price": 452.8,
          "exit_price": 523.4,
          "shares": 21439,
          "pnl": 1513593.3999999992,
          "pnl_pct": 0.15591872791519434,
          "impact_bps": 20.752,
          "phase": "out_of_sample",
          "composite_score": 0.8270893371757926
        },
        {
          "code": "19680",
          "entry_date": "2020-12-16",
          "exit_date": "2021-12-27",
          "entry_price": 791.0,
          "exit_price": 936.3,
          "shares": 12272,
          "pnl": 1783121.5999999994,
          "pnl_pct": 0.18369152970922875,
          "impact_bps": 53.246,
          "phase": "out_of_sample",
          "composite_score": 0.8227665706051873
        },
        {
          "code": "80880",
          "entry_date": "2020-12-16",
          "exit_date": "2021-12-27",
          "entry_price": 1510.0,
          "exit_price": 1405.0,
          "shares": 241,
          "pnl": -25305.0,
          "pnl_pct": -0.06953642384105962,
          "impact_bps": 26.3047,
          "phase": "out_of_sample",
          "composite_score": 0.8040345821325648
        },
        {
          "code": "50210",
          "entry_date": "2021-06-23",
          "exit_date": "2022-07-05",
          "entry_price": 1240.5,
          "exit_price": 1870.0,
          "shares": 9136,
          "pnl": 5751112.0,
          "pnl_pct": 0.5074566706972994,
          "impact_bps": 25.359,
          "phase": "out_of_sample",
          "composite_score": 0.9113372093023255
        },
        {
          "code": "94320",
          "entry_date": "2021-06-23",
          "exit_date": "2022-07-05",
          "entry_price": 114.7,
          "exit_price": 155.9,
          "shares": 73927,
          "pnl": 3045792.4000000004,
          "pnl_pct": 0.3591979075850045,
          "impact_bps": 10.1247,
          "phase": "out_of_sample",
          "composite_score": 0.8997093023255813
        },
        {
          "code": "18520",
          "entry_date": "2021-06-23",
          "exit_date": "2022-07-05",
          "entry_price": 450.0,
          "exit_price": 535.0,
          "shares": 942,
          "pnl": 80070.0,
          "pnl_pct": 0.18888888888888888,
          "impact_bps": 50.8667,
          "phase": "out_of_sample",
          "composite_score": 0.8924418604651163
        },
        {
          "code": "67580",
          "entry_date": "2021-12-27",
          "exit_date": "2022-07-05",
          "entry_price": 2873.0,
          "exit_price": 2221.0,
          "shares": 4373,
          "pnl": -2851196.0,
          "pnl_pct": -0.2269404803341455,
          "impact_bps": 8.7248,
          "phase": "out_of_sample",
          "composite_score": 0.8245614035087718
        },
        {
          "code": "91070",
          "entry_date": "2021-09-27",
          "exit_date": "2022-10-06",
          "entry_price": 868.9,
          "exit_price": 717.7,
          "shares": 14766,
          "pnl": -2232619.199999999,
          "pnl_pct": -0.17401312003682812,
          "impact_bps": 14.5445,
          "phase": "out_of_sample",
          "composite_score": 0.9273255813953488
        },
        {
          "code": "63230",
          "entry_date": "2021-09-27",
          "exit_date": "2022-10-06",
          "entry_price": 890.0,
          "exit_price": 809.0,
          "shares": 10650,
          "pnl": -862650.0,
          "pnl_pct": -0.09101123595505622,
          "impact_bps": 18.021,
          "phase": "out_of_sample",
          "composite_score": 0.875
        },
        {
          "code": "34430",
          "entry_date": "2021-09-27",
          "exit_date": "2022-10-06",
          "entry_price": 1336.7,
          "exit_price": 1253.3,
          "shares": 354,
          "pnl": -29523.60000000003,
          "pnl_pct": -0.06239245904092172,
          "impact_bps": 53.3378,
          "phase": "out_of_sample",
          "composite_score": 0.875
        },
        {
          "code": "79740",
          "entry_date": "2021-12-27",
          "exit_date": "2023-01-11",
          "entry_price": 5540.0,
          "exit_price": 5547.0,
          "shares": 2267,
          "pnl": 15869.0,
          "pnl_pct": 0.001263537906137202,
          "impact_bps": 8.6135,
          "phase": "out_of_sample",
          "composite_score": 0.9166666666666667
        },
        {
          "code": "93020",
          "entry_date": "2021-12-27",
          "exit_date": "2023-01-11",
          "entry_price": 800.7,
          "exit_price": 1188.3,
          "shares": 15692,
          "pnl": 6082219.199999998,
          "pnl_pct": 0.484076433121019,
          "impact_bps": 40.9975,
          "phase": "out_of_sample",
          "composite_score": 0.8903508771929824
        },
        {
          "code": "18850",
          "entry_date": "2021-12-27",
          "exit_date": "2023-01-11",
          "entry_price": 598.5,
          "exit_price": 581.3,
          "shares": 20993,
          "pnl": -361079.60000000097,
          "pnl_pct": -0.028738512949039285,
          "impact_bps": 26.0378,
          "phase": "out_of_sample",
          "composite_score": 0.8421052631578947
        },
        {
          "code": "63680",
          "entry_date": "2021-12-27",
          "exit_date": "2023-01-11",
          "entry_price": 1957.5,
          "exit_price": 3020.0,
          "shares": 6418,
          "pnl": 6819125.0,
          "pnl_pct": 0.5427841634738186,
          "impact_bps": 20.742,
          "phase": "out_of_sample",
          "composite_score": 0.8318713450292398
        },
        {
          "code": "72030",
          "entry_date": "2021-12-27",
          "exit_date": "2023-01-11",
          "entry_price": 2108.0,
          "exit_price": 1837.5,
          "shares": 5960,
          "pnl": -1612180.0,
          "pnl_pct": -0.12832068311195444,
          "impact_bps": 8.4663,
          "phase": "out_of_sample",
          "composite_score": 0.8172514619883041
        },
        {
          "code": "37910",
          "entry_date": "2021-12-27",
          "exit_date": "2023-01-11",
          "entry_price": 419.0,
          "exit_price": 529.8,
          "shares": 4135,
          "pnl": 458157.9999999998,
          "pnl_pct": 0.2644391408114557,
          "impact_bps": 70.7965,
          "phase": "out_of_sample",
          "composite_score": 0.8099415204678363
        },
        {
          "code": "91070",
          "entry_date": "2022-10-06",
          "exit_date": "2023-04-12",
          "entry_price": 717.7,
          "exit_price": 1123.3,
          "shares": 18763,
          "pnl": 7610272.799999998,
          "pnl_pct": 0.5651386373136407,
          "impact_bps": 14.7806,
          "phase": "out_of_sample",
          "composite_score": 0.9971014492753623
        },
        {
          "code": "50210",
          "entry_date": "2022-07-05",
          "exit_date": "2023-07-13",
          "entry_price": 1870.0,
          "exit_price": 1989.0,
          "shares": 7177,
          "pnl": 854063.0,
          "pnl_pct": 0.06363636363636371,
          "impact_bps": 27.1762,
          "phase": "out_of_sample",
          "composite_score": 0.8890489913544668
        },
        {
          "code": "94320",
          "entry_date": "2022-07-05",
          "exit_date": "2023-07-13",
          "entry_price": 155.9,
          "exit_price": 163.1,
          "shares": 86089,
          "pnl": 619840.799999999,
          "pnl_pct": 0.04618345093008336,
          "impact_bps": 10.581,
          "phase": "out_of_sample",
          "composite_score": 0.8832853025936599
        },
        {
          "code": "39970",
          "entry_date": "2022-07-05",
          "exit_date": "2023-07-13",
          "entry_price": 122.0,
          "exit_price": 94.6,
          "shares": 94028,
          "pnl": -2576367.2000000007,
          "pnl_pct": -0.22459016393442632,
          "impact_bps": 42.589,
          "phase": "out_of_sample",
          "composite_score": 0.8227665706051873
        },
        {
          "code": "19680",
          "entry_date": "2022-07-05",
          "exit_date": "2023-07-13",
          "entry_price": 973.3,
          "exit_price": 1403.3,
          "shares": 589,
          "pnl": 253270.0,
          "pnl_pct": 0.4417959519161616,
          "impact_bps": 61.8523,
          "phase": "out_of_sample",
          "composite_score": 0.8141210374639769
        },
        {
          "code": "63230",
          "entry_date": "2022-10-06",
          "exit_date": "2023-10-16",
          "entry_price": 809.0,
          "exit_price": 1156.0,
          "shares": 7305,
          "pnl": 2534835.0,
          "pnl_pct": 0.4289245982694685,
          "impact_bps": 18.3433,
          "phase": "out_of_sample",
          "composite_score": 0.9203652509005613
        },
        {
          "code": "69880",
          "entry_date": "2022-10-06",
          "exit_date": "2023-10-16",
          "entry_price": 1652.0,
          "exit_price": 1924.6,
          "shares": 179,
          "pnl": 48795.39999999999,
          "pnl_pct": 0.1650121065375303,
          "impact_bps": 14.5385,
          "phase": "out_of_sample",
          "composite_score": 0.8351218899220909
        },
        {
          "code": "91070",
          "entry_date": "2023-04-12",
          "exit_date": "2023-10-16",
          "entry_price": 1123.3,
          "exit_price": 1799.3,
          "shares": 13548,
          "pnl": 9158448.0,
          "pnl_pct": 0.6017982729457847,
          "impact_bps": 15.4039,
          "phase": "out_of_sample",
          "composite_score": 0.9914040114613181
        },
        {
          "code": "79740",
          "entry_date": "2023-01-11",
          "exit_date": "2024-01-19",
          "entry_price": 5547.0,
          "exit_price": 8136.0,
          "shares": 2523,
          "pnl": 6532047.0,
          "pnl_pct": 0.46673877771768524,
          "impact_bps": 8.8156,
          "phase": "out_of_sample",
          "composite_score": 0.9061693125218637
        },
        {
          "code": "93020",
          "entry_date": "2023-01-11",
          "exit_date": "2024-01-19",
          "entry_price": 1188.3,
          "exit_price": 1661.7,
          "shares": 11778,
          "pnl": 5575705.200000001,
          "pnl_pct": 0.39838424640242365,
          "impact_bps": 43.0196,
          "phase": "out_of_sample",
          "composite_score": 0.8398119305025737
        },
        {
          "code": "80880",
          "entry_date": "2023-01-11",
          "exit_date": "2024-01-19",
          "entry_price": 1400.0,
          "exit_price": 1652.0,
          "shares": 9997,
          "pnl": 2519244.0,
          "pnl_pct": 0.17999999999999994,
          "impact_bps": 30.6362,
          "phase": "out_of_sample",
          "composite_score": 0.8240658992853692
        },
        {
          "code": "50200",
          "entry_date": "2023-01-11",
          "exit_date": "2024-01-19",
          "entry_price": 453.4,
          "exit_price": 611.4,
          "shares": 30870,
          "pnl": 4877460.0,
          "pnl_pct": 0.3484781649757389,
          "impact_bps": 15.8054,
          "phase": "out_of_sample",
          "composite_score": 0.8080033649281204
        },
        {
          "code": "18520",
          "entry_date": "2023-01-11",
          "exit_date": "2024-01-19",
          "entry_price": 600.0,
          "exit_price": 832.0,
          "shares": 23328,
          "pnl": 5412096.0,
          "pnl_pct": 0.3866666666666667,
          "impact_bps": 56.0431,
          "phase": "out_of_sample",
          "composite_score": 0.8011235861471573
        },
        {
          "code": "67580",
          "entry_date": "2023-01-11",
          "exit_date": "2024-01-19",
          "entry_price": 2220.0,
          "exit_price": 2905.0,
          "shares": 2561,
          "pnl": 1754285.0,
          "pnl_pct": 0.3085585585585586,
          "impact_bps": 8.9331,
          "phase": "out_of_sample",
          "composite_score": 0.8008987023371259
        },
        {
          "code": "32310",
          "entry_date": "2023-01-11",
          "exit_date": "2024-01-19",
          "entry_price": 567.4,
          "exit_price": 803.0,
          "shares": 502,
          "pnl": 118271.20000000001,
          "pnl_pct": 0.41522735283750456,
          "impact_bps": 23.9524,
          "phase": "out_of_sample",
          "composite_score": 0.7996660058969532
        },
        {
          "code": "45950",
          "entry_date": "2023-07-13",
          "exit_date": "2024-01-19",
          "entry_price": 1019.5,
          "exit_price": 1777.5,
          "shares": 287,
          "pnl": 217546.0,
          "pnl_pct": 0.7435017165277096,
          "impact_bps": 78.0664,
          "phase": "out_of_sample",
          "composite_score": 0.8536931818181819
        },
        {
          "code": "77440",
          "entry_date": "2023-04-12",
          "exit_date": "2024-04-22",
          "entry_price": 737.3,
          "exit_price": 1006.7,
          "shares": 7567,
          "pnl": 2038549.8000000007,
          "pnl_pct": 0.36538722365387244,
          "impact_bps": 45.7543,
          "phase": "out_of_sample",
          "composite_score": 0.9842406876790831
        },
        {
          "code": "91470",
          "entry_date": "2023-04-12",
          "exit_date": "2024-04-22",
          "entry_price": 2596.7,
          "exit_price": 2673.3,
          "shares": 107,
          "pnl": 8196.200000000039,
          "pnl_pct": 0.02949897947394775,
          "impact_bps": 24.8971,
          "phase": "out_of_sample",
          "composite_score": 0.8638968481375358
        },
        {
          "code": "16620",
          "entry_date": "2023-07-13",
          "exit_date": "2024-04-22",
          "entry_price": 884.0,
          "exit_price": 1350.0,
          "shares": 18029,
          "pnl": 8401514.0,
          "pnl_pct": 0.5271493212669682,
          "impact_bps": 21.0032,
          "phase": "out_of_sample",
          "composite_score": 0.9076704545454546
        },
        {
          "code": "63230",
          "entry_date": "2023-10-16",
          "exit_date": "2024-04-22",
          "entry_price": 1156.0,
          "exit_price": 2497.0,
          "shares": 12674,
          "pnl": 16995834.0,
          "pnl_pct": 1.1600346020761245,
          "impact_bps": 20.3457,
          "phase": "out_of_sample",
          "composite_score": 0.953125
        },
        {
          "code": "94320",
          "entry_date": "2023-07-13",
          "exit_date": "2024-07-24",
          "entry_price": 163.1,
          "exit_price": 158.5,
          "shares": 97720,
          "pnl": -449511.9999999994,
          "pnl_pct": -0.028203556100551808,
          "impact_bps": 11.0865,
          "phase": "out_of_sample",
          "composite_score": 0.8821022727272727
        },
        {
          "code": "39970",
          "entry_date": "2023-07-13",
          "exit_date": "2024-07-24",
          "entry_price": 94.6,
          "exit_price": 89.7,
          "shares": 62045,
          "pnl": -304020.4999999995,
          "pnl_pct": -0.05179704016913311,
          "impact_bps": 46.0071,
          "phase": "out_of_sample",
          "composite_score": 0.8735795454545454
        },
        {
          "code": "91070",
          "entry_date": "2023-10-16",
          "exit_date": "2024-10-25",
          "entry_price": 1799.3,
          "exit_price": 2030.0,
          "shares": 9870,
          "pnl": 2277009.0000000005,
          "pnl_pct": 0.12821652865003053,
          "impact_bps": 16.2474,
          "phase": "out_of_sample",
          "composite_score": 0.9659090909090908
        },
        {
          "code": "19680",
          "entry_date": "2023-10-16",
          "exit_date": "2024-10-25",
          "entry_price": 1313.3,
          "exit_price": 1676.7,
          "shares": 558,
          "pnl": 202777.20000000004,
          "pnl_pct": 0.27670753064798603,
          "impact_bps": 70.526,
          "phase": "out_of_sample",
          "composite_score": 0.8508522727272727
        },
        {
          "code": "69660",
          "entry_date": "2024-01-19",
          "exit_date": "2024-10-25",
          "entry_price": 1383.2,
          "exit_price": 826.5,
          "shares": 14887,
          "pnl": -8287592.9,
          "pnl_pct": -0.4024725274725275,
          "impact_bps": 42.5236,
          "phase": "out_of_sample",
          "composite_score": 0.8465909090909092
        },
        {
          "code": "63230",
          "entry_date": "2024-04-22",
          "exit_date": "2024-10-25",
          "entry_price": 2497.0,
          "exit_price": 1985.0,
          "shares": 9012,
          "pnl": -4614144.0,
          "pnl_pct": -0.20504605526631958,
          "impact_bps": 22.2966,
          "phase": "out_of_sample",
          "composite_score": 0.8898305084745763
        },
        {
          "code": "93020",
          "entry_date": "2024-01-19",
          "exit_date": "2025-01-30",
          "entry_price": 1661.7,
          "exit_price": 2566.7,
          "shares": 12392,
          "pnl": 11214759.999999996,
          "pnl_pct": 0.54462297646988,
          "impact_bps": 51.2304,
          "phase": "out_of_sample",
          "composite_score": 0.8522727272727273
        },
        {
          "code": "69880",
          "entry_date": "2024-01-19",
          "exit_date": "2025-01-30",
          "entry_price": 2228.0,
          "exit_price": 2756.5,
          "shares": 9242,
          "pnl": 4884397.0,
          "pnl_pct": 0.23720825852782768,
          "impact_bps": 16.8201,
          "phase": "out_of_sample",
          "composite_score": 0.8394886363636364
        },
        {
          "code": "32310",
          "entry_date": "2024-01-19",
          "exit_date": "2025-01-30",
          "entry_price": 803.0,
          "exit_price": 848.2,
          "shares": 25644,
          "pnl": 1159108.8000000012,
          "pnl_pct": 0.05628891656288926,
          "impact_bps": 28.0384,
          "phase": "out_of_sample",
          "composite_score": 0.8238636363636365
        },
        {
          "code": "80880",
          "entry_date": "2024-01-19",
          "exit_date": "2025-01-30",
          "entry_price": 1652.0,
          "exit_price": 1699.5,
          "shares": 12031,
          "pnl": 571472.5,
          "pnl_pct": 0.028753026634382506,
          "impact_bps": 36.1672,
          "phase": "out_of_sample",
          "composite_score": 0.8210227272727273
        },
        {
          "code": "67580",
          "entry_date": "2024-01-19",
          "exit_date": "2025-01-30",
          "entry_price": 2905.0,
          "exit_price": 3452.0,
          "shares": 342,
          "pnl": 187074.0,
          "pnl_pct": 0.1882960413080894,
          "impact_bps": 9.7783,
          "phase": "out_of_sample",
          "composite_score": 0.8096590909090909
        },
        {
          "code": "16620",
          "entry_date": "2024-04-22",
          "exit_date": "2025-05-07",
          "entry_price": 1350.0,
          "exit_price": 1051.0,
          "shares": 16670,
          "pnl": -4984330.0,
          "pnl_pct": -0.2214814814814815,
          "impact_bps": 24.0523,
          "phase": "out_of_sample",
          "composite_score": 0.9166666666666667
        },
        {
          "code": "91040",
          "entry_date": "2024-04-22",
          "exit_date": "2025-05-07",
          "entry_price": 4729.0,
          "exit_price": 4675.0,
          "shares": 3803,
          "pnl": -205362.0,
          "pnl_pct": -0.01141890463100026,
          "impact_bps": 15.2186,
          "phase": "out_of_sample",
          "composite_score": 0.826271186440678
        },
        {
          "code": "18520",
          "entry_date": "2024-04-22",
          "exit_date": "2025-05-07",
          "entry_price": 746.0,
          "exit_price": 749.0,
          "shares": 1211,
          "pnl": 3633.0,
          "pnl_pct": 0.004021447721179516,
          "impact_bps": 69.934,
          "phase": "out_of_sample",
          "composite_score": 0.8093220338983051
        },
        {
          "code": "95040",
          "entry_date": "2024-07-24",
          "exit_date": "2025-05-07",
          "entry_price": 1016.0,
          "exit_price": 742.3,
          "shares": 19731,
          "pnl": -5400374.700000001,
          "pnl_pct": -0.2693897637795276,
          "impact_bps": 35.1064,
          "phase": "out_of_sample",
          "composite_score": 0.8806179775280899
        },
        {
          "code": "63230",
          "entry_date": "2024-10-25",
          "exit_date": "2025-05-07",
          "entry_price": 1985.0,
          "exit_price": 1475.0,
          "shares": 10473,
          "pnl": -5341230.0,
          "pnl_pct": -0.256926952141058,
          "impact_bps": 21.6176,
          "phase": "out_of_sample",
          "composite_score": 0.9131652661064426
        },
        {
          "code": "67030",
          "entry_date": "2024-07-24",
          "exit_date": "2025-08-05",
          "entry_price": 1024.0,
          "exit_price": 1619.0,
          "shares": 978,
          "pnl": 581910.0,
          "pnl_pct": 0.5810546875,
          "impact_bps": 42.2344,
          "phase": "out_of_sample",
          "composite_score": 0.8455056179775281
        },
        {
          "code": "69660",
          "entry_date": "2024-10-25",
          "exit_date": "2025-11-07",
          "entry_price": 826.5,
          "exit_price": 752.0,
          "shares": 25155,
          "pnl": -1874047.5,
          "pnl_pct": -0.09013914095583786,
          "impact_bps": 42.7062,
          "phase": "out_of_sample",
          "composite_score": 0.9033613445378151
        },
        {
          "code": "54100",
          "entry_date": "2024-10-25",
          "exit_date": "2025-11-07",
          "entry_price": 3865.0,
          "exit_price": 3625.0,
          "shares": 2369,
          "pnl": -568560.0,
          "pnl_pct": -0.0620957309184994,
          "impact_bps": 79.6636,
          "phase": "out_of_sample",
          "composite_score": 0.8235294117647058
        },
        {
          "code": "72800",
          "entry_date": "2024-10-25",
          "exit_date": "2025-11-07",
          "entry_price": 846.0,
          "exit_price": 953.0,
          "shares": 542,
          "pnl": 57994.0,
          "pnl_pct": 0.1264775413711583,
          "impact_bps": 28.2176,
          "phase": "out_of_sample",
          "composite_score": 0.8109243697478992
        }
      ]
    },
    "overfitting_ratio": 1.1981,
    "degradation_ratio": 0.8062,
    "passed_validation": "True"
  },
  "almgren_chriss_stats": {
    "total_calculations": 598
  },
  "selection_criteria": {
    "type": "percentile",
    "pbr_percentile": 0.25,
    "roe_percentile": 0.75,
    "composite_percentile": 0.75,
    "min_adt": 200000000
  },
  "trades_by_year": {
    "2008": 4,
    "2009": 12,
    "2010": 14,
    "2011": 14,
    "2012": 16,
    "2013": 16,
    "2014": 6,
    "2015": 18,
    "2016": 14,
    "2017": 17,
    "2018": 15,
    "2019": 14,
    "2020": 16,
    "2021": 14,
    "2022": 7,
    "2023": 14,
    "2024": 18,
    "2025": 14
  },
  "audit": {
    "total_checks": 9,
    "passed": 9,
    "failed": 0,
    "warnings": 0,
    "integrity_verified": true,
    "phase_checksums": {
      "training": "4efb3404164178d9",
      "validation": "b8b86ae8a8c5d96b",
      "out_of_sample": "e1adbe378ae10949"
    }
  }
}