{
  "segment_id": 1,
  "start_date": "2008-01-01",
  "end_date": "2011-12-31",
  "metrics": {
    "total_return": -0.17004963399999973,
    "cagr": -0.04982599778126151,
    "sharpe_ratio": -0.634384970329879,
    "sortino_ratio": -0.3424750346648973,
    "max_drawdown": 0.21136164582893782,
    "max_drawdown_date": "2008-09-16",
    "calmar_ratio": -0.23573812356470478,
    "win_rate": 0.023255813953488372,
    "profit_factor": 0.13047695266606052,
    "avg_monthly_return": -0.004421514781191199,
    "monthly_std": 0.01983013523760851,
    "best_month": 0.028529374112883144,
    "worst_month": -0.09259668410866828,
    "positive_months": 1,
    "negative_months": 3
  },
  "regime_stats": {
    "total_days": 837,
    "bull_days": 280,
    "bear_days": 501,
    "crisis_days": 56,
    "regime_changes": 48,
    "current_regime": "bear",
    "avg_vol_20d": 0.20948768119169098,
    "bull_pct": 0.3345280764635603,
    "bear_pct": 0.5985663082437276,
    "crisis_pct": 0.06690561529271206
  },
  "stress_tests": [
    {
      "period_name": "2008 GFC",
      "return_pct": -0.17004963399999973,
      "max_drawdown": 0.21136164582893782,
      "sharpe_ratio": -0.9433291674400097,
      "kill_switch_triggers": 1,
      "regime_distribution": {
        "bull": 0.24630541871921183,
        "bear": 0.6699507389162561,
        "crisis": 0.08374384236453201
      }
    },
    {
      "period_name": "2011 Earthquake",
      "return_pct": 0.0,
      "max_drawdown": 0,
      "sharpe_ratio": 0,
      "kill_switch_triggers": 0,
      "regime_distribution": {
        "bull": 0.40096618357487923,
        "bear": 0.4927536231884058,
        "crisis": 0.10628019323671498
      }
    }
  ],
  "equity_curve": [
    [
      "2008-05-07",
      100000000.0
    ],
    [
      "2008-05-08",
      100000000.0
    ],
    [
      "2008-05-09",
      100000000.0
    ],
    [
      "2008-05-12",
      100000000.0
    ],
    [
      "2008-05-13",
      100000000.0
    ],
    [
      "2008-05-14",
      100000000.0
    ],
    [
      "2008-05-15",
      100000000.0
    ],
    [
      "2008-05-16",
      100000000.0
    ],
    [
      "2008-05-19",
      100000000.0
    ],
    [
      "2008-05-20",
      100000000.0
    ],
    [
      "2008-05-21",
      100000000.0
    ],
    [
      "2008-05-22",
      100000000.0
    ],
    [
      "2008-05-23",
      100000000.0
    ],
    [
      "2008-05-26",
      100000000.0
    ],
    [
      "2008-05-27",
      100000000.0
    ],
    [
      "2008-05-28",
      98214736.0
    ],
    [
      "2008-05-29",
      99865518.0
    ],
    [
      "2008-05-30",
      101295091.0
    ],
    [
      "2008-06-02",
      102111182.0
    ],
    [
      "2008-06-03",
      101021245.0
    ],
    [
      "2008-06-04",
      103181489.0
    ],
    [
      "2008-06-05",
      102262195.0
    ],
    [
      "2008-06-06",
      102076432.0
    ],
    [
      "2008-06-09",
      101120700.0
    ],
    [
      "2008-06-10",
      99208477.0
    ],
    [
      "2008-06-11",
      99362064.0
    ],
    [
      "2008-06-12",
      97908865.0
    ],
    [
      "2008-06-13",
      97268535.0
    ],
    [
      "2008-06-16",
      98851977.0
    ],
    [
      "2008-06-17",
      99704535.0
    ],
    [
      "2008-06-18",
      103955107.8
    ],
    [
      "2008-06-19",
      105238397.5
    ],
    [
      "2008-06-20",
      100075476.8
    ],
    [
      "2008-06-23",
      103165728.8
    ],
    [
      "2008-06-24",
      102535574.3
    ],
    [
      "2008-06-25",
      101733916.0
    ],
    [
      "2008-06-26",
      98207067.0
    ],
    [
      "2008-06-27",
      97411722.3
    ],
    [
      "2008-06-30",
      94566158.0
    ],
    [
      "2008-07-01",
      94298504.0
    ],
    [
      "2008-07-02",
      92620989.5
    ],
    [
      "2008-07-03",
      91109521.0
    ],
    [
      "2008-07-04",
      92519159.5
    ],
    [
      "2008-07-07",
      94879443.5
    ],
    [
      "2008-07-08",
      93318757.9
    ],
    [
      "2008-07-09",
      93667225.9
    ],
    [
      "2008-07-10",
      94460848.5
    ],
    [
      "2008-07-11",
      93439787.9
    ],
    [
      "2008-07-14",
      93886193.5
    ],
    [
      "2008-07-15",
      92813580.9
    ],
    [
      "2008-07-16",
      91536130.9
    ],
    [
      "2008-07-17",
      93053239.9
    ],
    [
      "2008-07-18",
      91078310.5
    ],
    [
      "2008-07-22",
      91848968.9
    ],
    [
      "2008-07-23",
      94799713.9
    ],
    [
      "2008-07-24",
      96141746.5
    ],
    [
      "2008-07-25",
      96835161.5
    ],
    [
      "2008-07-28",
      98294814.9
    ],
    [
      "2008-07-29",
      97828913.4
    ],
    [
      "2008-07-30",
      99262384.30000001
    ],
    [
      "2008-07-31",
      97264071.30000001
    ],
    [
      "2008-08-01",
      96448282.4
    ],
    [
      "2008-08-04",
      94582960.80000001
    ],
    [
      "2008-08-05",
      93247249.30000001
    ],
    [
      "2008-08-06",
      96723702.9
    ],
    [
      "2008-08-07",
      95118519.10000001
    ],
    [
      "2008-08-08",
      95200466.9
    ],
    [
      "2008-08-11",
      95639672.0
    ],
    [
      "2008-08-12",
      93759395.60000001
    ],
    [
      "2008-08-13",
      92448131.50000001
    ],
    [
      "2008-08-14",
      91184003.00000001
    ],
    [
      "2008-08-15",
      92372567.70000002
    ],
    [
      "2008-08-18",
      92313088.9
    ],
    [
      "2008-08-19",
      91070631.9
    ],
    [
      "2008-08-20",
      91617353.70000002
    ],
    [
      "2008-08-21",
      90849393.30000001
    ],
    [
      "2008-08-22",
      90557880.50000001
    ],
    [
      "2008-08-25",
      90969159.9
    ],
    [
      "2008-08-26",
      91057535.60000002
    ],
    [
      "2008-08-27",
      90745297.30000001
    ],
    [
      "2008-08-28",
      90981598.10000002
    ],
    [
      "2008-08-29",
      91464330.30000003
    ],
    [
      "2008-09-01",
      90365295.30000003
    ],
    [
      "2008-09-02",
      89009557.80000003
    ],
    [
      "2008-09-03",
      87886497.60000002
    ],
    [
      "2008-09-04",
      86826042.10000002
    ],
    [
      "2008-09-05",
      85998524.60000002
    ],
    [
      "2008-09-08",
      87506126.10000002
    ],
    [
      "2008-09-09",
      86678764.60000002
    ],
    [
      "2008-09-10",
      87286044.10000002
    ],
    [
      "2008-09-11",
      85251039.10000002
    ],
    [
      "2008-09-12",
      85436064.60000002
    ],
    [
      "2008-09-16",
      82995036.60000002
    ],
    [
      "2008-09-17",
      82995036.60000002
    ],
    [
      "2008-09-18",
      82995036.60000002
    ],
    [
      "2008-09-19",
      82995036.60000002
    ],
    [
      "2008-09-22",
      82995036.60000002
    ],
    [
      "2008-09-24",
      82995036.60000002
    ],
    [
      "2008-09-25",
      82995036.60000002
    ],
    [
      "2008-09-26",
      82995036.60000002
    ],
    [
      "2008-09-29",
      82995036.60000002
    ],
    [
      "2008-09-30",
      82995036.60000002
    ],
    [
      "2008-10-01",
      82995036.60000002
    ],
    [
      "2008-10-02",
      82995036.60000002
    ],
    [
      "2008-10-03",
      82995036.60000002
    ],
    [
      "2008-10-06",
      82995036.60000002
    ],
    [
      "2008-10-07",
      82995036.60000002
    ],
    [
      "2008-10-08",
      82995036.60000002
    ],
    [
      "2008-10-09",
      82995036.60000002
    ],
    [
      "2008-10-10",
      82995036.60000002
    ],
    [
      "2008-10-14",
      82995036.60000002
    ],
    [
      "2008-10-15",
      82995036.60000002
    ],
    [
      "2008-10-16",
      82995036.60000002
    ],
    [
      "2008-10-17",
      82995036.60000002
    ],
    [
      "2008-10-20",
      82995036.60000002
    ],
    [
      "2008-10-21",
      82995036.60000002
    ],
    [
      "2008-10-22",
      82995036.60000002
    ],
    [
      "2008-10-23",
      82995036.60000002
    ],
    [
      "2008-10-24",
      82995036.60000002
    ],
    [
      "2008-10-27",
      82995036.60000002
    ],
    [
      "2008-10-28",
      82995036.60000002
    ],
    [
      "2008-10-29",
      82995036.60000002
    ],
    [
      "2008-10-30",
      82995036.60000002
    ],
    [
      "2008-10-31",
      82995036.60000002
    ],
    [
      "2008-11-04",
      82995036.60000002
    ],
    [
      "2008-11-05",
      82995036.60000002
    ],
    [
      "2008-11-06",
      82995036.60000002
    ],
    [
      "2008-11-07",
      82995036.60000002
    ],
    [
      "2008-11-10",
      82995036.60000002
    ],
    [
      "2008-11-11",
      82995036.60000002
    ],
    [
      "2008-11-12",
      82995036.60000002
    ],
    [
      "2008-11-13",
      82995036.60000002
    ],
    [
      "2008-11-14",
      82995036.60000002
    ],
    [
      "2008-11-17",
      82995036.60000002
    ],
    [
      "2008-11-18",
      82995036.60000002
    ],
    [
      "2008-11-19",
      82995036.60000002
    ],
    [
      "2008-11-20",
      82995036.60000002
    ],
    [
      "2008-11-21",
      82995036.60000002
    ],
    [
      "2008-11-25",
      82995036.60000002
    ],
    [
      "2008-11-26",
      82995036.60000002
    ],
    [
      "2008-11-27",
      82995036.60000002
    ],
    [
      "2008-11-28",
      82995036.60000002
    ],
    [
      "2008-12-01",
      82995036.60000002
    ],
    [
      "2008-12-02",
      82995036.60000002
    ],
    [
      "2008-12-03",
      82995036.60000002
    ],
    [
      "2008-12-04",
      82995036.60000002
    ],
    [
      "2008-12-05",
      82995036.60000002
    ],
    [
      "2008-12-08",
      82995036.60000002
    ],
    [
      "2008-12-09",
      82995036.60000002
    ],
    [
      "2008-12-10",
      82995036.60000002
    ],
    [
      "2008-12-11",
      82995036.60000002
    ],
    [
      "2008-12-12",
      82995036.60000002
    ],
    [
      "2008-12-15",
      82995036.60000002
    ],
    [
      "2008-12-16",
      82995036.60000002
    ],
    [
      "2008-12-17",
      82995036.60000002
    ],
    [
      "2008-12-18",
      82995036.60000002
    ],
    [
      "2008-12-19",
      82995036.60000002
    ],
    [
      "2008-12-22",
      82995036.60000002
    ],
    [
      "2008-12-24",
      82995036.60000002
    ],
    [
      "2008-12-25",
      82995036.60000002
    ],
    [
      "2008-12-26",
      82995036.60000002
    ],
    [
      "2008-12-29",
      82995036.60000002
    ],
    [
      "2008-12-30",
      82995036.60000002
    ],
    [
      "2009-01-05",
      82995036.60000002
    ],
    [
      "2009-01-06",
      82995036.60000002
    ],
    [
      "2009-01-07",
      82995036.60000002
    ],
    [
      "2009-01-08",
      82995036.60000002
    ],
    [
      "2009-01-09",
      82995036.60000002
    ],
    [
      "2009-01-13",
      82995036.60000002
    ],
    [
      "2009-01-14",
      82995036.60000002
    ],
    [
      "2009-01-15",
      82995036.60000002
    ],
    [
      "2009-01-16",
      82995036.60000002
    ],
    [
      "2009-01-19",
      82995036.60000002
    ],
    [
      "2009-01-20",
      82995036.60000002
    ],
    [
      "2009-01-21",
      82995036.60000002
    ],
    [
      "2009-01-22",
      82995036.60000002
    ],
    [
      "2009-01-23",
      82995036.60000002
    ],
    [
      "2009-01-26",
      82995036.60000002
    ],
    [
      "2009-01-27",
      82995036.60000002
    ],
    [
      "2009-01-28",
      82995036.60000002
    ],
    [
      "2009-01-29",
      82995036.60000002
    ],
    [
      "2009-01-30",
      82995036.60000002
    ],
    [
      "2009-02-02",
      82995036.60000002
    ],
    [
      "2009-02-03",
      82995036.60000002
    ],
    [
      "2009-02-04",
      82995036.60000002
    ],
    [
      "2009-02-05",
      82995036.60000002
    ],
    [
      "2009-02-06",
      82995036.60000002
    ],
    [
      "2009-02-09",
      82995036.60000002
    ],
    [
      "2009-02-10",
      82995036.60000002
    ],
    [
      "2009-02-12",
      82995036.60000002
    ],
    [
      "2009-02-13",
      82995036.60000002
    ],
    [
      "2009-02-16",
      82995036.60000002
    ],
    [
      "2009-02-17",
      82995036.60000002
    ],
    [
      "2009-02-18",
      82995036.60000002
    ],
    [
      "2009-02-19",
      82995036.60000002
    ],
    [
      "2009-02-20",
      82995036.60000002
    ],
    [
      "2009-02-23",
      82995036.60000002
    ],
    [
      "2009-02-24",
      82995036.60000002
    ],
    [
      "2009-02-25",
      82995036.60000002
    ],
    [
      "2009-02-26",
      82995036.60000002
    ],
    [
      "2009-02-27",
      82995036.60000002
    ],
    [
      "2009-03-02",
      82995036.60000002
    ],
    [
      "2009-03-03",
      82995036.60000002
    ],
    [
      "2009-03-04",
      82995036.60000002
    ],
    [
      "2009-03-05",
      82995036.60000002
    ],
    [
      "2009-03-06",
      82995036.60000002
    ],
    [
      "2009-03-09",
      82995036.60000002
    ],
    [
      "2009-03-10",
      82995036.60000002
    ],
    [
      "2009-03-11",
      82995036.60000002
    ],
    [
      "2009-03-12",
      82995036.60000002
    ],
    [
      "2009-03-13",
      82995036.60000002
    ],
    [
      "2009-03-16",
      82995036.60000002
    ],
    [
      "2009-03-17",
      82995036.60000002
    ],
    [
      "2009-03-18",
      82995036.60000002
    ],
    [
      "2009-03-19",
      82995036.60000002
    ],
    [
      "2009-03-23",
      82995036.60000002
    ],
    [
      "2009-03-24",
      82995036.60000002
    ],
    [
      "2009-03-25",
      82995036.60000002
    ],
    [
      "2009-03-26",
      82995036.60000002
    ],
    [
      "2009-03-27",
      82995036.60000002
    ],
    [
      "2009-03-30",
      82995036.60000002
    ],
    [
      "2009-03-31",
      82995036.60000002
    ],
    [
      "2009-04-01",
      82995036.60000002
    ],
    [
      "2009-04-02",
      82995036.60000002
    ],
    [
      "2009-04-03",
      82995036.60000002
    ],
    [
      "2009-04-06",
      82995036.60000002
    ],
    [
      "2009-04-07",
      82995036.60000002
    ],
    [
      "2009-04-08",
      82995036.60000002
    ],
    [
      "2009-04-09",
      82995036.60000002
    ],
    [
      "2009-04-10",
      82995036.60000002
    ],
    [
      "2009-04-13",
      82995036.60000002
    ],
    [
      "2009-04-14",
      82995036.60000002
    ],
    [
      "2009-04-15",
      82995036.60000002
    ],
    [
      "2009-04-16",
      82995036.60000002
    ],
    [
      "2009-04-17",
      82995036.60000002
    ],
    [
      "2009-04-20",
      82995036.60000002
    ],
    [
      "2009-04-21",
      82995036.60000002
    ],
    [
      "2009-04-22",
      82995036.60000002
    ],
    [
      "2009-04-23",
      82995036.60000002
    ],
    [
      "2009-04-24",
      82995036.60000002
    ],
    [
      "2009-04-27",
      82995036.60000002
    ],
    [
      "2009-04-28",
      82995036.60000002
    ],
    [
      "2009-04-30",
      82995036.60000002
    ],
    [
      "2009-05-01",
      82995036.60000002
    ],
    [
      "2009-05-07",
      82995036.60000002
    ],
    [
      "2009-05-08",
      82995036.60000002
    ],
    [
      "2009-05-11",
      82995036.60000002
    ],
    [
      "2009-05-12",
      82995036.60000002
    ],
    [
      "2009-05-13",
      82995036.60000002
    ],
    [
      "2009-05-14",
      82995036.60000002
    ],
    [
      "2009-05-15",
      82995036.60000002
    ],
    [
      "2009-05-18",
      82995036.60000002
    ],
    [
      "2009-05-19",
      82995036.60000002
    ],
    [
      "2009-05-20",
      82995036.60000002
    ],
    [
      "2009-05-21",
      82995036.60000002
    ],
    [
      "2009-05-22",
      82995036.60000002
    ],
    [
      "2009-05-25",
      82995036.60000002
    ],
    [
      "2009-05-26",
      82995036.60000002
    ],
    [
      "2009-05-27",
      82995036.60000002
    ],
    [
      "2009-05-28",
      82995036.60000002
    ],
    [
      "2009-05-29",
      82995036.60000002
    ],
    [
      "2009-06-01",
      82995036.60000002
    ],
    [
      "2009-06-02",
      82995036.60000002
    ],
    [
      "2009-06-03",
      82995036.60000002
    ],
    [
      "2009-06-04",
      82995036.60000002
    ],
    [
      "2009-06-05",
      82995036.60000002
    ],
    [
      "2009-06-08",
      82995036.60000002
    ],
    [
      "2009-06-09",
      82995036.60000002
    ],
    [
      "2009-06-10",
      82995036.60000002
    ],
    [
      "2009-06-11",
      82995036.60000002
    ],
    [
      "2009-06-12",
      82995036.60000002
    ],
    [
      "2009-06-15",
      82995036.60000002
    ],
    [
      "2009-06-16",
      82995036.60000002
    ],
    [
      "2009-06-17",
      82995036.60000002
    ],
    [
      "2009-06-18",
      82995036.60000002
    ],
    [
      "2009-06-19",
      82995036.60000002
    ],
    [
      "2009-06-22",
      82995036.60000002
    ],
    [
      "2009-06-23",
      82995036.60000002
    ],
    [
      "2009-06-24",
      82995036.60000002
    ],
    [
      "2009-06-25",
      82995036.60000002
    ],
    [
      "2009-06-26",
      82995036.60000002
    ],
    [
      "2009-06-29",
      82995036.60000002
    ],
    [
      "2009-06-30",
      82995036.60000002
    ],
    [
      "2009-07-01",
      82995036.60000002
    ],
    [
      "2009-07-02",
      82995036.60000002
    ],
    [
      "2009-07-03",
      82995036.60000002
    ],
    [
      "2009-07-06",
      82995036.60000002
    ],
    [
      "2009-07-07",
      82995036.60000002
    ],
    [
      "2009-07-08",
      82995036.60000002
    ],
    [
      "2009-07-09",
      82995036.60000002
    ],
    [
      "2009-07-10",
      82995036.60000002
    ],
    [
      "2009-07-13",
      82995036.60000002
    ],
    [
      "2009-07-14",
      82995036.60000002
    ],
    [
      "2009-07-15",
      82995036.60000002
    ],
    [
      "2009-07-16",
      82995036.60000002
    ],
    [
      "2009-07-17",
      82995036.60000002
    ],
    [
      "2009-07-21",
      82995036.60000002
    ],
    [
      "2009-07-22",
      82995036.60000002
    ],
    [
      "2009-07-23",
      82995036.60000002
    ],
    [
      "2009-07-24",
      82995036.60000002
    ],
    [
      "2009-07-27",
      82995036.60000002
    ],
    [
      "2009-07-28",
      82995036.60000002
    ],
    [
      "2009-07-29",
      82995036.60000002
    ],
    [
      "2009-07-30",
      82995036.60000002
    ],
    [
      "2009-07-31",
      82995036.60000002
    ],
    [
      "2009-08-03",
      82995036.60000002
    ],
    [
      "2009-08-04",
      82995036.60000002
    ],
    [
      "2009-08-05",
      82995036.60000002
    ],
    [
      "2009-08-06",
      82995036.60000002
    ],
    [
      "2009-08-07",
      82995036.60000002
    ],
    [
      "2009-08-10",
      82995036.60000002
    ],
    [
      "2009-08-11",
      82995036.60000002
    ],
    [
      "2009-08-12",
      82995036.60000002
    ],
    [
      "2009-08-13",
      82995036.60000002
    ],
    [
      "2009-08-14",
      82995036.60000002
    ],
    [
      "2009-08-17",
      82995036.60000002
    ],
    [
      "2009-08-18",
      82995036.60000002
    ],
    [
      "2009-08-19",
      82995036.60000002
    ],
    [
      "2009-08-20",
      82995036.60000002
    ],
    [
      "2009-08-21",
      82995036.60000002
    ],
    [
      "2009-08-24",
      82995036.60000002
    ],
    [
      "2009-08-25",
      82995036.60000002
    ],
    [
      "2009-08-26",
      82995036.60000002
    ],
    [
      "2009-08-27",
      82995036.60000002
    ],
    [
      "2009-08-28",
      82995036.60000002
    ],
    [
      "2009-08-31",
      82995036.60000002
    ],
    [
      "2009-09-01",
      82995036.60000002
    ],
    [
      "2009-09-02",
      82995036.60000002
    ],
    [
      "2009-09-03",
      82995036.60000002
    ],
    [
      "2009-09-04",
      82995036.60000002
    ],
    [
      "2009-09-07",
      82995036.60000002
    ],
    [
      "2009-09-08",
      82995036.60000002
    ],
    [
      "2009-09-09",
      82995036.60000002
    ],
    [
      "2009-09-10",
      82995036.60000002
    ],
    [
      "2009-09-11",
      82995036.60000002
    ],
    [
      "2009-09-14",
      82995036.60000002
    ],
    [
      "2009-09-15",
      82995036.60000002
    ],
    [
      "2009-09-16",
      82995036.60000002
    ],
    [
      "2009-09-17",
      82995036.60000002
    ],
    [
      "2009-09-18",
      82995036.60000002
    ],
    [
      "2009-09-24",
      82995036.60000002
    ],
    [
      "2009-09-25",
      82995036.60000002
    ],
    [
      "2009-09-28",
      82995036.60000002
    ],
    [
      "2009-09-29",
      82995036.60000002
    ],
    [
      "2009-09-30",
      82995036.60000002
    ],
    [
      "2009-10-01",
      82995036.60000002
    ],
    [
      "2009-10-02",
      82995036.60000002
    ],
    [
      "2009-10-05",
      82995036.60000002
    ],
    [
      "2009-10-06",
      82995036.60000002
    ],
    [
      "2009-10-07",
      82995036.60000002
    ],
    [
      "2009-10-08",
      82995036.60000002
    ],
    [
      "2009-10-09",
      82995036.60000002
    ],
    [
      "2009-10-13",
      82995036.60000002
    ],
    [
      "2009-10-14",
      82995036.60000002
    ],
    [
      "2009-10-15",
      82995036.60000002
    ],
    [
      "2009-10-16",
      82995036.60000002
    ],
    [
      "2009-10-19",
      82995036.60000002
    ],
    [
      "2009-10-20",
      82995036.60000002
    ],
    [
      "2009-10-21",
      82995036.60000002
    ],
    [
      "2009-10-22",
      82995036.60000002
    ],
    [
      "2009-10-23",
      82995036.60000002
    ],
    [
      "2009-10-26",
      82995036.60000002
    ],
    [
      "2009-10-27",
      82995036.60000002
    ],
    [
      "2009-10-28",
      82995036.60000002
    ],
    [
      "2009-10-29",
      82995036.60000002
    ],
    [
      "2009-10-30",
      82995036.60000002
    ],
    [
      "2009-11-02",
      82995036.60000002
    ],
    [
      "2009-11-04",
      82995036.60000002
    ],
    [
      "2009-11-05",
      82995036.60000002
    ],
    [
      "2009-11-06",
      82995036.60000002
    ],
    [
      "2009-11-09",
      82995036.60000002
    ],
    [
      "2009-11-10",
      82995036.60000002
    ],
    [
      "2009-11-11",
      82995036.60000002
    ],
    [
      "2009-11-12",
      82995036.60000002
    ],
    [
      "2009-11-13",
      82995036.60000002
    ],
    [
      "2009-11-16",
      82995036.60000002
    ],
    [
      "2009-11-17",
      82995036.60000002
    ],
    [
      "2009-11-18",
      82995036.60000002
    ],
    [
      "2009-11-19",
      82995036.60000002
    ],
    [
      "2009-11-20",
      82995036.60000002
    ],
    [
      "2009-11-24",
      82995036.60000002
    ],
    [
      "2009-11-25",
      82995036.60000002
    ],
    [
      "2009-11-26",
      82995036.60000002
    ],
    [
      "2009-11-27",
      82995036.60000002
    ],
    [
      "2009-11-30",
      82995036.60000002
    ],
    [
      "2009-12-01",
      82995036.60000002
    ],
    [
      "2009-12-02",
      82995036.60000002
    ],
    [
      "2009-12-03",
      82995036.60000002
    ],
    [
      "2009-12-04",
      82995036.60000002
    ],
    [
      "2009-12-07",
      82995036.60000002
    ],
    [
      "2009-12-08",
      82995036.60000002
    ],
    [
      "2009-12-09",
      82995036.60000002
    ],
    [
      "2009-12-10",
      82995036.60000002
    ],
    [
      "2009-12-11",
      82995036.60000002
    ],
    [
      "2009-12-14",
      82995036.60000002
    ],
    [
      "2009-12-15",
      82995036.60000002
    ],
    [
      "2009-12-16",
      82995036.60000002
    ],
    [
      "2009-12-17",
      82995036.60000002
    ],
    [
      "2009-12-18",
      82995036.60000002
    ],
    [
      "2009-12-21",
      82995036.60000002
    ],
    [
      "2009-12-22",
      82995036.60000002
    ],
    [
      "2009-12-24",
      82995036.60000002
    ],
    [
      "2009-12-25",
      82995036.60000002
    ],
    [
      "2009-12-28",
      82995036.60000002
    ],
    [
      "2009-12-29",
      82995036.60000002
    ],
    [
      "2009-12-30",
      82995036.60000002
    ],
    [
      "2010-01-04",
      82995036.60000002
    ],
    [
      "2010-01-05",
      82995036.60000002
    ],
    [
      "2010-01-06",
      82995036.60000002
    ],
    [
      "2010-01-07",
      82995036.60000002
    ],
    [
      "2010-01-08",
      82995036.60000002
    ],
    [
      "2010-01-12",
      82995036.60000002
    ],
    [
      "2010-01-13",
      82995036.60000002
    ],
    [
      "2010-01-14",
      82995036.60000002
    ],
    [
      "2010-01-15",
      82995036.60000002
    ],
    [
      "2010-01-18",
      82995036.60000002
    ],
    [
      "2010-01-19",
      82995036.60000002
    ],
    [
      "2010-01-20",
      82995036.60000002
    ],
    [
      "2010-01-21",
      82995036.60000002
    ],
    [
      "2010-01-22",
      82995036.60000002
    ],
    [
      "2010-01-25",
      82995036.60000002
    ],
    [
      "2010-01-26",
      82995036.60000002
    ],
    [
      "2010-01-27",
      82995036.60000002
    ],
    [
      "2010-01-28",
      82995036.60000002
    ],
    [
      "2010-01-29",
      82995036.60000002
    ],
    [
      "2010-02-01",
      82995036.60000002
    ],
    [
      "2010-02-02",
      82995036.60000002
    ],
    [
      "2010-02-03",
      82995036.60000002
    ],
    [
      "2010-02-04",
      82995036.60000002
    ],
    [
      "2010-02-05",
      82995036.60000002
    ],
    [
      "2010-02-08",
      82995036.60000002
    ],
    [
      "2010-02-09",
      82995036.60000002
    ],
    [
      "2010-02-10",
      82995036.60000002
    ],
    [
      "2010-02-12",
      82995036.60000002
    ],
    [
      "2010-02-15",
      82995036.60000002
    ],
    [
      "2010-02-16",
      82995036.60000002
    ],
    [
      "2010-02-17",
      82995036.60000002
    ],
    [
      "2010-02-18",
      82995036.60000002
    ],
    [
      "2010-02-19",
      82995036.60000002
    ],
    [
      "2010-02-22",
      82995036.60000002
    ],
    [
      "2010-02-23",
      82995036.60000002
    ],
    [
      "2010-02-24",
      82995036.60000002
    ],
    [
      "2010-02-25",
      82995036.60000002
    ],
    [
      "2010-02-26",
      82995036.60000002
    ],
    [
      "2010-03-01",
      82995036.60000002
    ],
    [
      "2010-03-02",
      82995036.60000002
    ],
    [
      "2010-03-03",
      82995036.60000002
    ],
    [
      "2010-03-04",
      82995036.60000002
    ],
    [
      "2010-03-05",
      82995036.60000002
    ],
    [
      "2010-03-08",
      82995036.60000002
    ],
    [
      "2010-03-09",
      82995036.60000002
    ],
    [
      "2010-03-10",
      82995036.60000002
    ],
    [
      "2010-03-11",
      82995036.60000002
    ],
    [
      "2010-03-12",
      82995036.60000002
    ],
    [
      "2010-03-15",
      82995036.60000002
    ],
    [
      "2010-03-16",
      82995036.60000002
    ],
    [
      "2010-03-17",
      82995036.60000002
    ],
    [
      "2010-03-18",
      82995036.60000002
    ],
    [
      "2010-03-19",
      82995036.60000002
    ],
    [
      "2010-03-23",
      82995036.60000002
    ],
    [
      "2010-03-24",
      82995036.60000002
    ],
    [
      "2010-03-25",
      82995036.60000002
    ],
    [
      "2010-03-26",
      82995036.60000002
    ],
    [
      "2010-03-29",
      82995036.60000002
    ],
    [
      "2010-03-30",
      82995036.60000002
    ],
    [
      "2010-03-31",
      82995036.60000002
    ],
    [
      "2010-04-01",
      82995036.60000002
    ],
    [
      "2010-04-02",
      82995036.60000002
    ],
    [
      "2010-04-05",
      82995036.60000002
    ],
    [
      "2010-04-06",
      82995036.60000002
    ],
    [
      "2010-04-07",
      82995036.60000002
    ],
    [
      "2010-04-08",
      82995036.60000002
    ],
    [
      "2010-04-09",
      82995036.60000002
    ],
    [
      "2010-04-12",
      82995036.60000002
    ],
    [
      "2010-04-13",
      82995036.60000002
    ],
    [
      "2010-04-14",
      82995036.60000002
    ],
    [
      "2010-04-15",
      82995036.60000002
    ],
    [
      "2010-04-16",
      82995036.60000002
    ],
    [
      "2010-04-19",
      82995036.60000002
    ],
    [
      "2010-04-20",
      82995036.60000002
    ],
    [
      "2010-04-21",
      82995036.60000002
    ],
    [
      "2010-04-22",
      82995036.60000002
    ],
    [
      "2010-04-23",
      82995036.60000002
    ],
    [
      "2010-04-26",
      82995036.60000002
    ],
    [
      "2010-04-27",
      82995036.60000002
    ],
    [
      "2010-04-28",
      82995036.60000002
    ],
    [
      "2010-04-30",
      82995036.60000002
    ],
    [
      "2010-05-06",
      82995036.60000002
    ],
    [
      "2010-05-07",
      82995036.60000002
    ],
    [
      "2010-05-10",
      82995036.60000002
    ],
    [
      "2010-05-11",
      82995036.60000002
    ],
    [
      "2010-05-12",
      82995036.60000002
    ],
    [
      "2010-05-13",
      82995036.60000002
    ],
    [
      "2010-05-14",
      82995036.60000002
    ],
    [
      "2010-05-17",
      82995036.60000002
    ],
    [
      "2010-05-18",
      82995036.60000002
    ],
    [
      "2010-05-19",
      82995036.60000002
    ],
    [
      "2010-05-20",
      82995036.60000002
    ],
    [
      "2010-05-21",
      82995036.60000002
    ],
    [
      "2010-05-24",
      82995036.60000002
    ],
    [
      "2010-05-25",
      82995036.60000002
    ],
    [
      "2010-05-26",
      82995036.60000002
    ],
    [
      "2010-05-27",
      82995036.60000002
    ],
    [
      "2010-05-28",
      82995036.60000002
    ],
    [
      "2010-05-31",
      82995036.60000002
    ],
    [
      "2010-06-01",
      82995036.60000002
    ],
    [
      "2010-06-02",
      82995036.60000002
    ],
    [
      "2010-06-03",
      82995036.60000002
    ],
    [
      "2010-06-04",
      82995036.60000002
    ],
    [
      "2010-06-07",
      82995036.60000002
    ],
    [
      "2010-06-08",
      82995036.60000002
    ],
    [
      "2010-06-09",
      82995036.60000002
    ],
    [
      "2010-06-10",
      82995036.60000002
    ],
    [
      "2010-06-11",
      82995036.60000002
    ],
    [
      "2010-06-14",
      82995036.60000002
    ],
    [
      "2010-06-15",
      82995036.60000002
    ],
    [
      "2010-06-16",
      82995036.60000002
    ],
    [
      "2010-06-17",
      82995036.60000002
    ],
    [
      "2010-06-18",
      82995036.60000002
    ],
    [
      "2010-06-21",
      82995036.60000002
    ],
    [
      "2010-06-22",
      82995036.60000002
    ],
    [
      "2010-06-23",
      82995036.60000002
    ],
    [
      "2010-06-24",
      82995036.60000002
    ],
    [
      "2010-06-25",
      82995036.60000002
    ],
    [
      "2010-06-28",
      82995036.60000002
    ],
    [
      "2010-06-29",
      82995036.60000002
    ],
    [
      "2010-06-30",
      82995036.60000002
    ],
    [
      "2010-07-01",
      82995036.60000002
    ],
    [
      "2010-07-02",
      82995036.60000002
    ],
    [
      "2010-07-05",
      82995036.60000002
    ],
    [
      "2010-07-06",
      82995036.60000002
    ],
    [
      "2010-07-07",
      82995036.60000002
    ],
    [
      "2010-07-08",
      82995036.60000002
    ],
    [
      "2010-07-09",
      82995036.60000002
    ],
    [
      "2010-07-12",
      82995036.60000002
    ],
    [
      "2010-07-13",
      82995036.60000002
    ],
    [
      "2010-07-14",
      82995036.60000002
    ],
    [
      "2010-07-15",
      82995036.60000002
    ],
    [
      "2010-07-16",
      82995036.60000002
    ],
    [
      "2010-07-20",
      82995036.60000002
    ],
    [
      "2010-07-21",
      82995036.60000002
    ],
    [
      "2010-07-22",
      82995036.60000002
    ],
    [
      "2010-07-23",
      82995036.60000002
    ],
    [
      "2010-07-26",
      82995036.60000002
    ],
    [
      "2010-07-27",
      82995036.60000002
    ],
    [
      "2010-07-28",
      82995036.60000002
    ],
    [
      "2010-07-29",
      82995036.60000002
    ],
    [
      "2010-07-30",
      82995036.60000002
    ],
    [
      "2010-08-02",
      82995036.60000002
    ],
    [
      "2010-08-03",
      82995036.60000002
    ],
    [
      "2010-08-04",
      82995036.60000002
    ],
    [
      "2010-08-05",
      82995036.60000002
    ],
    [
      "2010-08-06",
      82995036.60000002
    ],
    [
      "2010-08-09",
      82995036.60000002
    ],
    [
      "2010-08-10",
      82995036.60000002
    ],
    [
      "2010-08-11",
      82995036.60000002
    ],
    [
      "2010-08-12",
      82995036.60000002
    ],
    [
      "2010-08-13",
      82995036.60000002
    ],
    [
      "2010-08-16",
      82995036.60000002
    ],
    [
      "2010-08-17",
      82995036.60000002
    ],
    [
      "2010-08-18",
      82995036.60000002
    ],
    [
      "2010-08-19",
      82995036.60000002
    ],
    [
      "2010-08-20",
      82995036.60000002
    ],
    [
      "2010-08-23",
      82995036.60000002
    ],
    [
      "2010-08-24",
      82995036.60000002
    ],
    [
      "2010-08-25",
      82995036.60000002
    ],
    [
      "2010-08-26",
      82995036.60000002
    ],
    [
      "2010-08-27",
      82995036.60000002
    ],
    [
      "2010-08-30",
      82995036.60000002
    ],
    [
      "2010-08-31",
      82995036.60000002
    ],
    [
      "2010-09-01",
      82995036.60000002
    ],
    [
      "2010-09-02",
      82995036.60000002
    ],
    [
      "2010-09-03",
      82995036.60000002
    ],
    [
      "2010-09-06",
      82995036.60000002
    ],
    [
      "2010-09-07",
      82995036.60000002
    ],
    [
      "2010-09-08",
      82995036.60000002
    ],
    [
      "2010-09-09",
      82995036.60000002
    ],
    [
      "2010-09-10",
      82995036.60000002
    ],
    [
      "2010-09-13",
      82995036.60000002
    ],
    [
      "2010-09-14",
      82995036.60000002
    ],
    [
      "2010-09-15",
      82995036.60000002
    ],
    [
      "2010-09-16",
      82995036.60000002
    ],
    [
      "2010-09-17",
      82995036.60000002
    ],
    [
      "2010-09-21",
      82995036.60000002
    ],
    [
      "2010-09-22",
      82995036.60000002
    ],
    [
      "2010-09-24",
      82995036.60000002
    ],
    [
      "2010-09-27",
      82995036.60000002
    ],
    [
      "2010-09-28",
      82995036.60000002
    ],
    [
      "2010-09-29",
      82995036.60000002
    ],
    [
      "2010-09-30",
      82995036.60000002
    ],
    [
      "2010-10-01",
      82995036.60000002
    ],
    [
      "2010-10-04",
      82995036.60000002
    ],
    [
      "2010-10-05",
      82995036.60000002
    ],
    [
      "2010-10-06",
      82995036.60000002
    ],
    [
      "2010-10-07",
      82995036.60000002
    ],
    [
      "2010-10-08",
      82995036.60000002
    ],
    [
      "2010-10-12",
      82995036.60000002
    ],
    [
      "2010-10-13",
      82995036.60000002
    ],
    [
      "2010-10-14",
      82995036.60000002
    ],
    [
      "2010-10-15",
      82995036.60000002
    ],
    [
      "2010-10-18",
      82995036.60000002
    ],
    [
      "2010-10-19",
      82995036.60000002
    ],
    [
      "2010-10-20",
      82995036.60000002
    ],
    [
      "2010-10-21",
      82995036.60000002
    ],
    [
      "2010-10-22",
      82995036.60000002
    ],
    [
      "2010-10-25",
      82995036.60000002
    ],
    [
      "2010-10-26",
      82995036.60000002
    ],
    [
      "2010-10-27",
      82995036.60000002
    ],
    [
      "2010-10-28",
      82995036.60000002
    ],
    [
      "2010-10-29",
      82995036.60000002
    ],
    [
      "2010-11-01",
      82995036.60000002
    ],
    [
      "2010-11-02",
      82995036.60000002
    ],
    [
      "2010-11-04",
      82995036.60000002
    ],
    [
      "2010-11-05",
      82995036.60000002
    ],
    [
      "2010-11-08",
      82995036.60000002
    ],
    [
      "2010-11-09",
      82995036.60000002
    ],
    [
      "2010-11-10",
      82995036.60000002
    ],
    [
      "2010-11-11",
      82995036.60000002
    ],
    [
      "2010-11-12",
      82995036.60000002
    ],
    [
      "2010-11-15",
      82995036.60000002
    ],
    [
      "2010-11-16",
      82995036.60000002
    ],
    [
      "2010-11-17",
      82995036.60000002
    ],
    [
      "2010-11-18",
      82995036.60000002
    ],
    [
      "2010-11-19",
      82995036.60000002
    ],
    [
      "2010-11-22",
      82995036.60000002
    ],
    [
      "2010-11-24",
      82995036.60000002
    ],
    [
      "2010-11-25",
      82995036.60000002
    ],
    [
      "2010-11-26",
      82995036.60000002
    ],
    [
      "2010-11-29",
      82995036.60000002
    ],
    [
      "2010-11-30",
      82995036.60000002
    ],
    [
      "2010-12-01",
      82995036.60000002
    ],
    [
      "2010-12-02",
      82995036.60000002
    ],
    [
      "2010-12-03",
      82995036.60000002
    ],
    [
      "2010-12-06",
      82995036.60000002
    ],
    [
      "2010-12-07",
      82995036.60000002
    ],
    [
      "2010-12-08",
      82995036.60000002
    ],
    [
      "2010-12-09",
      82995036.60000002
    ],
    [
      "2010-12-10",
      82995036.60000002
    ],
    [
      "2010-12-13",
      82995036.60000002
    ],
    [
      "2010-12-14",
      82995036.60000002
    ],
    [
      "2010-12-15",
      82995036.60000002
    ],
    [
      "2010-12-16",
      82995036.60000002
    ],
    [
      "2010-12-17",
      82995036.60000002
    ],
    [
      "2010-12-20",
      82995036.60000002
    ],
    [
      "2010-12-21",
      82995036.60000002
    ],
    [
      "2010-12-22",
      82995036.60000002
    ],
    [
      "2010-12-24",
      82995036.60000002
    ],
    [
      "2010-12-27",
      82995036.60000002
    ],
    [
      "2010-12-28",
      82995036.60000002
    ],
    [
      "2010-12-29",
      82995036.60000002
    ],
    [
      "2010-12-30",
      82995036.60000002
    ],
    [
      "2011-01-04",
      82995036.60000002
    ],
    [
      "2011-01-05",
      82995036.60000002
    ],
    [
      "2011-01-06",
      82995036.60000002
    ],
    [
      "2011-01-07",
      82995036.60000002
    ],
    [
      "2011-01-11",
      82995036.60000002
    ],
    [
      "2011-01-12",
      82995036.60000002
    ],
    [
      "2011-01-13",
      82995036.60000002
    ],
    [
      "2011-01-14",
      82995036.60000002
    ],
    [
      "2011-01-17",
      82995036.60000002
    ],
    [
      "2011-01-18",
      82995036.60000002
    ],
    [
      "2011-01-19",
      82995036.60000002
    ],
    [
      "2011-01-20",
      82995036.60000002
    ],
    [
      "2011-01-21",
      82995036.60000002
    ],
    [
      "2011-01-24",
      82995036.60000002
    ],
    [
      "2011-01-25",
      82995036.60000002
    ],
    [
      "2011-01-26",
      82995036.60000002
    ],
    [
      "2011-01-27",
      82995036.60000002
    ],
    [
      "2011-01-28",
      82995036.60000002
    ],
    [
      "2011-01-31",
      82995036.60000002
    ],
    [
      "2011-02-01",
      82995036.60000002
    ],
    [
      "2011-02-02",
      82995036.60000002
    ],
    [
      "2011-02-03",
      82995036.60000002
    ],
    [
      "2011-02-04",
      82995036.60000002
    ],
    [
      "2011-02-07",
      82995036.60000002
    ],
    [
      "2011-02-08",
      82995036.60000002
    ],
    [
      "2011-02-09",
      82995036.60000002
    ],
    [
      "2011-02-10",
      82995036.60000002
    ],
    [
      "2011-02-14",
      82995036.60000002
    ],
    [
      "2011-02-15",
      82995036.60000002
    ],
    [
      "2011-02-16",
      82995036.60000002
    ],
    [
      "2011-02-17",
      82995036.60000002
    ],
    [
      "2011-02-18",
      82995036.60000002
    ],
    [
      "2011-02-21",
      82995036.60000002
    ],
    [
      "2011-02-22",
      82995036.60000002
    ],
    [
      "2011-02-23",
      82995036.60000002
    ],
    [
      "2011-02-24",
      82995036.60000002
    ],
    [
      "2011-02-25",
      82995036.60000002
    ],
    [
      "2011-02-28",
      82995036.60000002
    ],
    [
      "2011-03-01",
      82995036.60000002
    ],
    [
      "2011-03-02",
      82995036.60000002
    ],
    [
      "2011-03-03",
      82995036.60000002
    ],
    [
      "2011-03-04",
      82995036.60000002
    ],
    [
      "2011-03-07",
      82995036.60000002
    ],
    [
      "2011-03-08",
      82995036.60000002
    ],
    [
      "2011-03-09",
      82995036.60000002
    ],
    [
      "2011-03-10",
      82995036.60000002
    ],
    [
      "2011-03-11",
      82995036.60000002
    ],
    [
      "2011-03-14",
      82995036.60000002
    ],
    [
      "2011-03-15",
      82995036.60000002
    ],
    [
      "2011-03-16",
      82995036.60000002
    ],
    [
      "2011-03-17",
      82995036.60000002
    ],
    [
      "2011-03-18",
      82995036.60000002
    ],
    [
      "2011-03-22",
      82995036.60000002
    ],
    [
      "2011-03-23",
      82995036.60000002
    ],
    [
      "2011-03-24",
      82995036.60000002
    ],
    [
      "2011-03-25",
      82995036.60000002
    ],
    [
      "2011-03-28",
      82995036.60000002
    ],
    [
      "2011-03-29",
      82995036.60000002
    ],
    [
      "2011-03-30",
      82995036.60000002
    ],
    [
      "2011-03-31",
      82995036.60000002
    ],
    [
      "2011-04-01",
      82995036.60000002
    ],
    [
      "2011-04-04",
      82995036.60000002
    ],
    [
      "2011-04-05",
      82995036.60000002
    ],
    [
      "2011-04-06",
      82995036.60000002
    ],
    [
      "2011-04-07",
      82995036.60000002
    ],
    [
      "2011-04-08",
      82995036.60000002
    ],
    [
      "2011-04-11",
      82995036.60000002
    ],
    [
      "2011-04-12",
      82995036.60000002
    ],
    [
      "2011-04-13",
      82995036.60000002
    ],
    [
      "2011-04-14",
      82995036.60000002
    ],
    [
      "2011-04-15",
      82995036.60000002
    ],
    [
      "2011-04-18",
      82995036.60000002
    ],
    [
      "2011-04-19",
      82995036.60000002
    ],
    [
      "2011-04-20",
      82995036.60000002
    ],
    [
      "2011-04-21",
      82995036.60000002
    ],
    [
      "2011-04-22",
      82995036.60000002
    ],
    [
      "2011-04-25",
      82995036.60000002
    ],
    [
      "2011-04-26",
      82995036.60000002
    ],
    [
      "2011-04-27",
      82995036.60000002
    ],
    [
      "2011-04-28",
      82995036.60000002
    ],
    [
      "2011-05-02",
      82995036.60000002
    ],
    [
      "2011-05-06",
      82995036.60000002
    ],
    [
      "2011-05-09",
      82995036.60000002
    ],
    [
      "2011-05-10",
      82995036.60000002
    ],
    [
      "2011-05-11",
      82995036.60000002
    ],
    [
      "2011-05-12",
      82995036.60000002
    ],
    [
      "2011-05-13",
      82995036.60000002
    ],
    [
      "2011-05-16",
      82995036.60000002
    ],
    [
      "2011-05-17",
      82995036.60000002
    ],
    [
      "2011-05-18",
      82995036.60000002
    ],
    [
      "2011-05-19",
      82995036.60000002
    ],
    [
      "2011-05-20",
      82995036.60000002
    ],
    [
      "2011-05-23",
      82995036.60000002
    ],
    [
      "2011-05-24",
      82995036.60000002
    ],
    [
      "2011-05-25",
      82995036.60000002
    ],
    [
      "2011-05-26",
      82995036.60000002
    ],
    [
      "2011-05-27",
      82995036.60000002
    ],
    [
      "2011-05-30",
      82995036.60000002
    ],
    [
      "2011-05-31",
      82995036.60000002
    ],
    [
      "2011-06-01",
      82995036.60000002
    ],
    [
      "2011-06-02",
      82995036.60000002
    ],
    [
      "2011-06-03",
      82995036.60000002
    ],
    [
      "2011-06-06",
      82995036.60000002
    ],
    [
      "2011-06-07",
      82995036.60000002
    ],
    [
      "2011-06-08",
      82995036.60000002
    ],
    [
      "2011-06-09",
      82995036.60000002
    ],
    [
      "2011-06-10",
      82995036.60000002
    ],
    [
      "2011-06-13",
      82995036.60000002
    ],
    [
      "2011-06-14",
      82995036.60000002
    ],
    [
      "2011-06-15",
      82995036.60000002
    ],
    [
      "2011-06-16",
      82995036.60000002
    ],
    [
      "2011-06-17",
      82995036.60000002
    ],
    [
      "2011-06-20",
      82995036.60000002
    ],
    [
      "2011-06-21",
      82995036.60000002
    ],
    [
      "2011-06-22",
      82995036.60000002
    ],
    [
      "2011-06-23",
      82995036.60000002
    ],
    [
      "2011-06-24",
      82995036.60000002
    ],
    [
      "2011-06-27",
      82995036.60000002
    ],
    [
      "2011-06-28",
      82995036.60000002
    ],
    [
      "2011-06-29",
      82995036.60000002
    ],
    [
      "2011-06-30",
      82995036.60000002
    ],
    [
      "2011-07-01",
      82995036.60000002
    ],
    [
      "2011-07-04",
      82995036.60000002
    ],
    [
      "2011-07-05",
      82995036.60000002
    ],
    [
      "2011-07-06",
      82995036.60000002
    ],
    [
      "2011-07-07",
      82995036.60000002
    ],
    [
      "2011-07-08",
      82995036.60000002
    ],
    [
      "2011-07-11",
      82995036.60000002
    ],
    [
      "2011-07-12",
      82995036.60000002
    ],
    [
      "2011-07-13",
      82995036.60000002
    ],
    [
      "2011-07-14",
      82995036.60000002
    ],
    [
      "2011-07-15",
      82995036.60000002
    ],
    [
      "2011-07-19",
      82995036.60000002
    ],
    [
      "2011-07-20",
      82995036.60000002
    ],
    [
      "2011-07-21",
      82995036.60000002
    ],
    [
      "2011-07-22",
      82995036.60000002
    ],
    [
      "2011-07-25",
      82995036.60000002
    ],
    [
      "2011-07-26",
      82995036.60000002
    ],
    [
      "2011-07-27",
      82995036.60000002
    ],
    [
      "2011-07-28",
      82995036.60000002
    ],
    [
      "2011-07-29",
      82995036.60000002
    ],
    [
      "2011-08-01",
      82995036.60000002
    ],
    [
      "2011-08-02",
      82995036.60000002
    ],
    [
      "2011-08-03",
      82995036.60000002
    ],
    [
      "2011-08-04",
      82995036.60000002
    ],
    [
      "2011-08-05",
      82995036.60000002
    ],
    [
      "2011-08-08",
      82995036.60000002
    ],
    [
      "2011-08-09",
      82995036.60000002
    ],
    [
      "2011-08-10",
      82995036.60000002
    ],
    [
      "2011-08-11",
      82995036.60000002
    ],
    [
      "2011-08-12",
      82995036.60000002
    ],
    [
      "2011-08-15",
      82995036.60000002
    ],
    [
      "2011-08-16",
      82995036.60000002
    ],
    [
      "2011-08-17",
      82995036.60000002
    ],
    [
      "2011-08-18",
      82995036.60000002
    ],
    [
      "2011-08-19",
      82995036.60000002
    ],
    [
      "2011-08-22",
      82995036.60000002
    ],
    [
      "2011-08-23",
      82995036.60000002
    ],
    [
      "2011-08-24",
      82995036.60000002
    ],
    [
      "2011-08-25",
      82995036.60000002
    ],
    [
      "2011-08-26",
      82995036.60000002
    ],
    [
      "2011-08-29",
      82995036.60000002
    ],
    [
      "2011-08-30",
      82995036.60000002
    ],
    [
      "2011-08-31",
      82995036.60000002
    ],
    [
      "2011-09-01",
      82995036.60000002
    ],
    [
      "2011-09-02",
      82995036.60000002
    ],
    [
      "2011-09-05",
      82995036.60000002
    ],
    [
      "2011-09-06",
      82995036.60000002
    ],
    [
      "2011-09-07",
      82995036.60000002
    ],
    [
      "2011-09-08",
      82995036.60000002
    ],
    [
      "2011-09-09",
      82995036.60000002
    ],
    [
      "2011-09-12",
      82995036.60000002
    ],
    [
      "2011-09-13",
      82995036.60000002
    ],
    [
      "2011-09-14",
      82995036.60000002
    ],
    [
      "2011-09-15",
      82995036.60000002
    ],
    [
      "2011-09-16",
      82995036.60000002
    ],
    [
      "2011-09-20",
      82995036.60000002
    ],
    [
      "2011-09-21",
      82995036.60000002
    ],
    [
      "2011-09-22",
      82995036.60000002
    ],
    [
      "2011-09-26",
      82995036.60000002
    ],
    [
      "2011-09-27",
      82995036.60000002
    ],
    [
      "2011-09-28",
      82995036.60000002
    ],
    [
      "2011-09-29",
      82995036.60000002
    ],
    [
      "2011-09-30",
      82995036.60000002
    ],
    [
      "2011-10-03",
      82995036.60000002
    ],
    [
      "2011-10-04",
      82995036.60000002
    ],
    [
      "2011-10-05",
      82995036.60000002
    ],
    [
      "2011-10-06",
      82995036.60000002
    ],
    [
      "2011-10-07",
      82995036.60000002
    ],
    [
      "2011-10-11",
      82995036.60000002
    ],
    [
      "2011-10-12",
      82995036.60000002
    ],
    [
      "2011-10-13",
      82995036.60000002
    ],
    [
      "2011-10-14",
      82995036.60000002
    ],
    [
      "2011-10-17",
      82995036.60000002
    ],
    [
      "2011-10-18",
      82995036.60000002
    ],
    [
      "2011-10-19",
      82995036.60000002
    ],
    [
      "2011-10-20",
      82995036.60000002
    ],
    [
      "2011-10-21",
      82995036.60000002
    ],
    [
      "2011-10-24",
      82995036.60000002
    ],
    [
      "2011-10-25",
      82995036.60000002
    ],
    [
      "2011-10-26",
      82995036.60000002
    ],
    [
      "2011-10-27",
      82995036.60000002
    ],
    [
      "2011-10-28",
      82995036.60000002
    ],
    [
      "2011-10-31",
      82995036.60000002
    ],
    [
      "2011-11-01",
      82995036.60000002
    ],
    [
      "2011-11-02",
      82995036.60000002
    ],
    [
      "2011-11-04",
      82995036.60000002
    ],
    [
      "2011-11-07",
      82995036.60000002
    ],
    [
      "2011-11-08",
      82995036.60000002
    ],
    [
      "2011-11-09",
      82995036.60000002
    ],
    [
      "2011-11-10",
      82995036.60000002
    ],
    [
      "2011-11-11",
      82995036.60000002
    ],
    [
      "2011-11-14",
      82995036.60000002
    ],
    [
      "2011-11-15",
      82995036.60000002
    ],
    [
      "2011-11-16",
      82995036.60000002
    ],
    [
      "2011-11-17",
      82995036.60000002
    ],
    [
      "2011-11-18",
      82995036.60000002
    ],
    [
      "2011-11-21",
      82995036.60000002
    ],
    [
      "2011-11-22",
      82995036.60000002
    ],
    [
      "2011-11-24",
      82995036.60000002
    ],
    [
      "2011-11-25",
      82995036.60000002
    ],
    [
      "2011-11-28",
      82995036.60000002
    ],
    [
      "2011-11-29",
      82995036.60000002
    ],
    [
      "2011-11-30",
      82995036.60000002
    ],
    [
      "2011-12-01",
      82995036.60000002
    ],
    [
      "2011-12-02",
      82995036.60000002
    ],
    [
      "2011-12-05",
      82995036.60000002
    ],
    [
      "2011-12-06",
      82995036.60000002
    ],
    [
      "2011-12-07",
      82995036.60000002
    ],
    [
      "2011-12-08",
      82995036.60000002
    ],
    [
      "2011-12-09",
      82995036.60000002
    ],
    [
      "2011-12-12",
      82995036.60000002
    ],
    [
      "2011-12-13",
      82995036.60000002
    ],
    [
      "2011-12-14",
      82995036.60000002
    ],
    [
      "2011-12-15",
      82995036.60000002
    ],
    [
      "2011-12-16",
      82995036.60000002
    ],
    [
      "2011-12-19",
      82995036.60000002
    ],
    [
      "2011-12-20",
      82995036.60000002
    ],
    [
      "2011-12-21",
      82995036.60000002
    ],
    [
      "2011-12-22",
      82995036.60000002
    ],
    [
      "2011-12-26",
      82995036.60000002
    ],
    [
      "2011-12-27",
      82995036.60000002
    ],
    [
      "2011-12-28",
      82995036.60000002
    ],
    [
      "2011-12-29",
      82995036.60000002
    ],
    [
      "2011-12-30",
      82995036.60000002
    ]
  ],
  "monthly_returns": [
    [
      "2008-06-30",
      -0.06642901382062039
    ],
    [
      "2008-07-31",
      0.028529374112883144
    ],
    [
      "2008-08-31",
      -0.05962881177481605
    ],
    [
      "2008-09-30",
      -0.09259668410866828
    ],
    [
      "2008-10-31",
      0.0
    ],
    [
      "2008-11-30",
      0.0
    ],
    [
      "2008-12-31",
      0.0
    ],
    [
      "2009-01-31",
      0.0
    ],
    [
      "2009-02-28",
      0.0
    ],
    [
      "2009-03-31",
      0.0
    ],
    [
      "2009-04-30",
      0.0
    ],
    [
      "2009-05-31",
      0.0
    ],
    [
      "2009-06-30",
      0.0
    ],
    [
      "2009-07-31",
      0.0
    ],
    [
      "2009-08-31",
      0.0
    ],
    [
      "2009-09-30",
      0.0
    ],
    [
      "2009-10-31",
      0.0
    ],
    [
      "2009-11-30",
      0.0
    ],
    [
      "2009-12-31",
      0.0
    ],
    [
      "2010-01-31",
      0.0
    ],
    [
      "2010-02-28",
      0.0
    ],
    [
      "2010-03-31",
      0.0
    ],
    [
      "2010-04-30",
      0.0
    ],
    [
      "2010-05-31",
      0.0
    ],
    [
      "2010-06-30",
      0.0
    ],
    [
      "2010-07-31",
      0.0
    ],
    [
      "2010-08-31",
      0.0
    ],
    [
      "2010-09-30",
      0.0
    ],
    [
      "2010-10-31",
      0.0
    ],
    [
      "2010-11-30",
      0.0
    ],
    [
      "2010-12-31",
      0.0
    ],
    [
      "2011-01-31",
      0.0
    ],
    [
      "2011-02-28",
      0.0
    ],
    [
      "2011-03-31",
      0.0
    ],
    [
      "2011-04-30",
      0.0
    ],
    [
      "2011-05-31",
      0.0
    ],
    [
      "2011-06-30",
      0.0
    ],
    [
      "2011-07-31",
      0.0
    ],
    [
      "2011-08-31",
      0.0
    ],
    [
      "2011-09-30",
      0.0
    ],
    [
      "2011-10-31",
      0.0
    ],
    [
      "2011-11-30",
      0.0
    ],
    [
      "2011-12-31",
      0.0
    ]
  ],
  "trade_count": 272
}